{"_id": "CPSF:entity=1065:block=2400_approved_undefined", "context": "D1065S2400", "_model": "collation", "display_settings": {"view_supplied": true, "show_punctuation": false, "show_xml": false, "view_capitalisation": false, "use_lemma": true, "view_unclear": true, "expand_abbreviations": true}, "structure": {"marked_readings": {"regularised": [{"identifier": ["r"], "subreading": [false], "witness": "D", "apparatus": "apparatus", "suffixed_label": [false], "value": "regularised", "suffixed_sigla": [true], "end": 8, "parent_text": "que lo", "start": 6, "reading_history": ["quelo"], "name": ["Regularised"], "reading_text": "quelo", "unit_id": "c1b8bb3686b314b65ec8bdb56e66d161"}, {"identifier": ["r"], "subreading": [false], "witness": "S", "apparatus": "apparatus", "suffixed_label": [false], "value": "regularised", "suffixed_sigla": [true], "end": 8, "parent_text": "que lo", "start": 6, "reading_history": ["quelo"], "name": ["Regularised"], "reading_text": "quelo", "unit_id": "c1b8bb3686b314b65ec8bdb56e66d161"}, {"identifier": ["r"], "subreading": [false], "witness": "Ss", "apparatus": "apparatus", "suffixed_label": [false], "value": "regularised", "suffixed_sigla": [true], "end": 8, "parent_text": "que lo", "start": 6, "reading_history": ["quelo"], "name": ["Regularised"], "reading_text": "quelo", "unit_id": "c1b8bb3686b314b65ec8bdb56e66d161"}], "none": [{"identifier": [null], "subreading": [false], "witness": "F", "apparatus": "apparatus", "suffixed_label": [false], "value": "none", "suffixed_sigla": [false], "end": 1, "parent_text": "&lt;lac&gt;", "start": 1, "details": "lac verse", "type": "lac_verse", "reading_history": ["&lt;lac verse&gt;"], "name": ["None"], "reading_text": "&lt;lac verse&gt;", "om_details": "lac", "unit_id": "900b0858d6eedebeca7c1680fa687098"}, {"identifier": [null], "subreading": [false], "witness": "F", "apparatus": "apparatus", "suffixed_label": [false], "value": "none", "suffixed_sigla": [false], "end": 4, "parent_text": "&lt;lac&gt;", "start": 2, "details": "lac verse", "type": "lac_verse", "reading_history": ["&lt;lac verse&gt;"], "name": ["None"], "reading_text": "&lt;lac verse&gt;", "om_details": "lac", "unit_id": "762efbafd7c20e5190b7f449b2e61a68"}, {"identifier": [null], "subreading": [false], "witness": "F", "apparatus": "apparatus", "suffixed_label": [false], "value": "none", "suffixed_sigla": [false], "end": 8, "parent_text": "&lt;lac&gt;", "start": 6, "details": "lac verse", "type": "lac_verse", "reading_history": ["&lt;lac verse&gt;"], "name": ["None"], "reading_text": "&lt;lac verse&gt;", "om_details": "lac", "unit_id": "c1b8bb3686b314b65ec8bdb56e66d161"}, {"identifier": [null], "subreading": [false], "witness": "F", "apparatus": "apparatus", "suffixed_label": [false], "value": "none", "suffixed_sigla": [false], "end": 10, "parent_text": "&lt;lac&gt;", "start": 10, "details": "lac verse", "type": "lac_verse", "reading_history": ["&lt;lac verse&gt;"], "name": ["None"], "reading_text": "&lt;lac verse&gt;", "om_details": "lac", "unit_id": "94116edf37aed5188794c2eaa6715561"}, {"identifier": [null], "subreading": [false], "witness": "F", "apparatus": "apparatus", "suffixed_label": [false], "value": "none", "suffixed_sigla": [false], "end": 12, "parent_text": "&lt;lac&gt;", "start": 12, "details": "lac verse", "type": "lac_verse", "reading_history": ["&lt;lac verse&gt;"], "name": ["None"], "reading_text": "&lt;lac verse&gt;", "om_details": "lac", "unit_id": "f1a54659313c74230a30375635d9c821"}, {"identifier": [null], "subreading": [false], "witness": "F", "apparatus": "apparatus", "suffixed_label": [false], "value": "none", "suffixed_sigla": [false], "end": 44, "parent_text": "&lt;lac&gt;", "start": 14, "details": "lac verse", "type": "lac_verse", "reading_history": ["&lt;lac verse&gt;"], "name": ["None"], "reading_text": "&lt;lac verse&gt;", "om_details": "lac", "unit_id": "e14e8ccf36c4f583af7fd13973468f16"}, {"identifier": [null], "subreading": [false], "witness": "F", "apparatus": "apparatus", "suffixed_label": [false], "value": "none", "suffixed_sigla": [false], "end": 46, "parent_text": "&lt;lac&gt;", "start": 46, "details": "lac verse", "type": "lac_verse", "reading_history": ["&lt;lac verse&gt;"], "name": ["None"], "reading_text": "&lt;lac verse&gt;", "om_details": "lac", "unit_id": "2b81b9bec1ffafa1fcc4d185d2bfdf0f"}, {"identifier": [null], "subreading": [false], "witness": "F", "apparatus": "apparatus", "suffixed_label": [false], "value": "none", "suffixed_sigla": [false], "end": 52, "parent_text": "&lt;lac&gt;", "start": 48, "details": "lac verse", "type": "lac_verse", "reading_history": ["&lt;lac verse&gt;"], "name": ["None"], "reading_text": "&lt;lac verse&gt;", "om_details": "lac", "unit_id": "9986ab3b57942b27990856e8c0058c16"}, {"identifier": [null], "subreading": [false], "witness": "F", "apparatus": "apparatus", "suffixed_label": [false], "value": "none", "suffixed_sigla": [false], "end": 54, "parent_text": "&lt;lac&gt;", "start": 54, "details": "lac verse", "type": "lac_verse", "reading_history": ["&lt;lac verse&gt;"], "name": ["None"], "reading_text": "&lt;lac verse&gt;", "om_details": "lac", "unit_id": "dbdd0cdd5fce3cda9eff784b05ccdd0f"}, {"identifier": [null], "subreading": [false], "witness": "F", "apparatus": "apparatus", "suffixed_label": [false], "value": "none", "suffixed_sigla": [false], "end": 58, "parent_text": "&lt;lac&gt;", "start": 56, "details": "lac verse", "type": "lac_verse", "reading_history": ["&lt;lac verse&gt;"], "name": ["None"], "reading_text": "&lt;lac verse&gt;", "om_details": "lac", "unit_id": "34844b33976132c3eb7b35698a650da0"}, {"identifier": [null], "subreading": [false], "witness": "F", "apparatus": "apparatus", "suffixed_label": [false], "value": "none", "suffixed_sigla": [false], "end": 70, "parent_text": "&lt;lac&gt;", "start": 60, "details": "lac verse", "type": "lac_verse", "reading_history": ["&lt;lac verse&gt;"], "name": ["None"], "reading_text": "&lt;lac verse&gt;", "om_details": "lac", "unit_id": "862d62df95aed79e23a25c61a937796d"}, {"identifier": [null], "subreading": [false], "witness": "F", "apparatus": "apparatus", "suffixed_label": [false], "value": "none", "suffixed_sigla": [false], "end": 72, "parent_text": "&lt;lac&gt;", "start": 72, "details": "lac verse", "type": "lac_verse", "reading_history": ["&lt;lac verse&gt;"], "name": ["None"], "reading_text": "&lt;lac verse&gt;", "om_details": "lac", "unit_id": "78c826149be483896e47929644623c4f"}, {"identifier": [null], "subreading": [false], "witness": "F", "apparatus": "apparatus", "suffixed_label": [false], "value": "none", "suffixed_sigla": [false], "end": 80, "parent_text": "&lt;lac&gt;", "start": 74, "details": "lac verse", "type": "lac_verse", "reading_history": ["&lt;lac verse&gt;"], "name": ["None"], "reading_text": "&lt;lac verse&gt;", "om_details": "lac", "unit_id": "f5ab8d5c344c3caba2310508674e4599"}, {"identifier": [null], "subreading": [false], "witness": "F", "apparatus": "apparatus", "suffixed_label": [false], "value": "none", "suffixed_sigla": [false], "end": 82, "parent_text": "&lt;lac&gt;", "start": 82, "details": "lac verse", "type": "lac_verse", "reading_history": ["&lt;lac verse&gt;"], "name": ["None"], "reading_text": "&lt;lac verse&gt;", "om_details": "lac", "unit_id": "f0b6604f0dc9538a28b3621d7b77d941"}, {"identifier": [null], "subreading": [false], "witness": "F", "apparatus": "apparatus", "suffixed_label": [false], "value": "none", "suffixed_sigla": [false], "end": 94, "parent_text": "&lt;lac&gt;", "start": 84, "details": "lac verse", "type": "lac_verse", "reading_history": ["&lt;lac verse&gt;"], "name": ["None"], "reading_text": "&lt;lac verse&gt;", "om_details": "lac", "unit_id": "809014ef6697f1f33ac4da30f78e452b"}, {"identifier": [null], "subreading": [false], "witness": "F", "apparatus": "apparatus", "suffixed_label": [false], "value": "none", "suffixed_sigla": [false], "end": 96, "parent_text": "&lt;lac&gt;", "start": 96, "details": "lac verse", "type": "lac_verse", "reading_history": ["&lt;lac verse&gt;"], "name": ["None"], "reading_text": "&lt;lac verse&gt;", "om_details": "lac", "unit_id": "314fb4d9469898bb8155840814986e92"}, {"identifier": [null], "subreading": [false], "witness": "F", "apparatus": "apparatus", "suffixed_label": [false], "value": "none", "suffixed_sigla": [false], "end": 110, "parent_text": "&lt;lac&gt;", "start": 98, "details": "lac verse", "type": "lac_verse", "reading_history": ["&lt;lac verse&gt;"], "name": ["None"], "reading_text": "&lt;lac verse&gt;", "om_details": "lac", "unit_id": "94de4f790b2f9acc22ce51323ead3a27"}, {"identifier": [null], "subreading": [false], "witness": "F", "apparatus": "apparatus", "suffixed_label": [false], "value": "none", "suffixed_sigla": [false], "end": 112, "parent_text": "&lt;lac&gt;", "start": 112, "details": "lac verse", "type": "lac_verse", "reading_history": ["&lt;lac verse&gt;"], "name": ["None"], "reading_text": "&lt;lac verse&gt;", "om_details": "lac", "unit_id": "ec13c9c36494d18c8c384cb0a897d98d"}]}, "hand_id_map": {"Ss": "Ss", "F": "F", "E2": "E2", "S": "S", "D": "D"}, "overtext_name": "E2", "overtext": [{"tokens": [{"original": "el", "pc_before": "\u00b6&nbsp;", "index": "2", "rule_match": ["el"], "reading": "E2", "t": "el"}, {"original": "primero", "index": "4", "rule_match": ["primero"], "reading": "E2", "t": "primero"}, {"original": "q\u0304", "fullxml": "q<am>\u0304</am><ex>ue</ex>", "expanded": "que", "index": "6", "rule_match": ["que", "q\u0304", "q<am>\u0304</am><ex>ue</ex>"], "reading": "E2", "t": "q\u0304"}, {"original": "lo", "index": "8", "rule_match": ["lo"], "reading": "E2", "t": "lo"}, {"original": "cometio", "index": "10", "rule_match": ["cometio"], "reading": "E2", "t": "cometio"}, {"original": "\u204a", "fullxml": "<am>\u204a</am><ex>e</ex>", "expanded": "e", "index": "12", "rule_match": ["e", "\u204a", "<am>\u204a</am><ex>e</ex>"], "reading": "E2", "t": "\u204a"}, {"original": "abrio", "index": "14", "rule_match": ["abrio"], "reading": "E2", "t": "abrio"}, {"original": "la", "index": "16", "rule_match": ["la"], "reading": "E2", "t": "la"}, {"original": "carrera", "index": "18", "rule_match": ["carrera"], "reading": "E2", "t": "carrera"}, {"original": "alos", "index": "20", "rule_match": ["alos"], "reading": "E2", "t": "alos"}, {"original": "otros", "index": "22", "rule_match": ["otros"], "reading": "E2", "t": "otros"}, {"original": "\u204a", "fullxml": "<am>\u204a</am><ex>e</ex>", "expanded": "e", "index": "24", "rule_match": ["e", "\u204a", "<am>\u204a</am><ex>e</ex>"], "reading": "E2", "t": "\u204a"}, {"original": "el", "index": "26", "rule_match": ["el"], "reading": "E2", "t": "el"}, {"original": "q\u0304", "fullxml": "q<am>\u0304</am><ex>ue</ex>", "expanded": "que", "index": "28", "rule_match": ["que", "q\u0304", "q<am>\u0304</am><ex>ue</ex>"], "reading": "E2", "t": "q\u0304"}, {"original": "ante", "index": "30", "rule_match": ["ante"], "reading": "E2", "t": "ante"}, {"original": "subio", "index": "32", "rule_match": ["subio"], "reading": "E2", "t": "subio"}, {"original": "por", "index": "34", "rule_match": ["por"], "reading": "E2", "t": "por"}, {"original": "la", "index": "36", "rule_match": ["la"], "reading": "E2", "t": "la"}, {"original": "pen\u0304a", "fullxml": "pen<am>\u0304</am><ex>n</ex>a", "expanded": "penna", "index": "38", "rule_match": ["penna", "pen\u0304a", "pen<am>\u0304</am><ex>n</ex>a"], "reading": "E2", "t": "pen\u0304a"}, {"original": "arriba", "index": "40", "rule_match": ["arriba"], "reading": "E2", "t": "arriba"}, {"original": "fue", "index": "42", "rule_match": ["fue"], "reading": "E2", "t": "fue"}, {"original": "diego", "index": "44", "rule_match": ["diego"], "reading": "E2", "t": "diego"}, {"original": "perez", "index": "46", "rule_match": ["perez"], "reading": "E2", "t": "perez"}, {"original": "machuca", "index": "48", "rule_match": ["machuca"], "reading": "E2", "t": "machuca"}, {"original": "\u204a", "fullxml": "<am>\u204a</am><ex>e</ex>", "expanded": "e", "index": "50", "rule_match": ["e", "\u204a", "<am>\u204a</am><ex>e</ex>"], "reading": "E2", "t": "\u204a"}, {"original": "murieron", "index": "52", "rule_match": ["murieron"], "reading": "E2", "t": "murieron"}, {"original": "y", "index": "54", "rule_match": ["y"], "reading": "E2", "t": "y"}, {"original": "de", "index": "56", "rule_match": ["de"], "reading": "E2", "t": "de"}, {"original": "aqu\u0304ellos", "fullxml": "aqu<am>\u0304</am><ex>e</ex>ellos", "expanded": "aqueellos", "index": "58", "rule_match": ["aqueellos", "aqu\u0304ellos", "aqu<am>\u0304</am><ex>e</ex>ellos"], "reading": "E2", "t": "aqu\u0304ellos"}, {"original": "q\u1d45renta", "fullxml": "q<am>\u1d45</am><ex>ua</ex>renta", "expanded": "quarenta", "index": "60", "rule_match": ["quarenta", "q\u1d45renta", "q<am>\u1d45</am><ex>ua</ex>renta"], "reading": "E2", "t": "q\u1d45renta"}, {"original": "\u204a", "fullxml": "<am>\u204a</am><ex>e</ex>", "expanded": "e", "index": "62", "rule_match": ["e", "\u204a", "<am>\u204a</am><ex>e</ex>"], "reading": "E2", "t": "\u204a"}, {"original": "ci\u0304co", "fullxml": "ci<am>\u0304</am><ex>n</ex>co", "expanded": "cinco", "index": "64", "rule_match": ["cinco", "ci\u0304co", "ci<am>\u0304</am><ex>n</ex>co"], "reading": "E2", "t": "ci\u0304co"}, {"original": "caualleros", "index": "66", "rule_match": ["caualleros"], "reading": "E2", "t": "caualleros"}, {"original": "los", "index": "68", "rule_match": ["los"], "reading": "E2", "t": "los"}, {"original": "q\u0304", "fullxml": "q<am>\u0304</am><ex>ue</ex>", "expanded": "que", "index": "70", "rule_match": ["que", "q\u0304", "q<am>\u0304</am><ex>ue</ex>"], "reading": "E2", "t": "q\u0304"}, {"original": "destaiaron", "index": "72", "rule_match": ["destaiaron"], "reading": "E2", "t": "destaiaron"}, {"original": "los", "index": "74", "rule_match": ["los"], "reading": "E2", "t": "los"}, {"original": "moros", "index": "76", "rule_match": ["moros"], "reading": "E2", "t": "moros"}, {"original": "que", "index": "78", "rule_match": ["que"], "reading": "E2", "t": "que"}, {"original": "non", "index": "80", "rule_match": ["non"], "reading": "E2", "t": "non"}, {"original": "podieron", "index": "82", "rule_match": ["podieron"], "reading": "E2", "t": "podieron"}, {"original": "pasar", "index": "84", "rule_match": ["pasar"], "reading": "E2", "t": "pasar"}, {"original": "\u204a", "fullxml": "<am>\u204a</am><ex>e</ex>", "expanded": "e", "index": "86", "rule_match": ["e", "\u204a", "<am>\u204a</am><ex>e</ex>"], "reading": "E2", "t": "\u204a"}, {"original": "los", "index": "88", "rule_match": ["los"], "reading": "E2", "t": "los"}, {"original": "otros", "index": "90", "rule_match": ["otros"], "reading": "E2", "t": "otros"}, {"original": "pasaron", "index": "92", "rule_match": ["pasaron"], "reading": "E2", "t": "pasaron"}, {"original": "\u204a", "fullxml": "<am>\u204a</am><ex>e</ex>", "expanded": "e", "index": "94", "rule_match": ["e", "\u204a", "<am>\u204a</am><ex>e</ex>"], "reading": "E2", "t": "\u204a"}, {"original": "sobieron", "index": "96", "rule_match": ["sobieron"], "reading": "E2", "t": "sobieron"}, {"original": "por", "index": "98", "rule_match": ["por"], "reading": "E2", "t": "por"}, {"original": "la", "index": "100", "rule_match": ["la"], "reading": "E2", "t": "la"}, {"original": "pe\u0304na", "fullxml": "pe<am>\u0304</am><ex>n</ex>na", "expanded": "penna", "index": "102", "rule_match": ["penna", "pe\u0304na", "pe<am>\u0304</am><ex>n</ex>na"], "reading": "E2", "t": "pe\u0304na"}, {"original": "arriba", "index": "104", "rule_match": ["arriba"], "reading": "E2", "t": "arriba"}, {"original": "\u204a", "fullxml": "<am>\u204a</am><ex>e</ex>", "expanded": "e", "index": "106", "rule_match": ["e", "\u204a", "<am>\u204a</am><ex>e</ex>"], "reading": "E2", "t": "\u204a"}, {"original": "entraron", "index": "108", "rule_match": ["entraron"], "reading": "E2", "t": "entraron"}, {"original": "enl\u0304enl", "fullxml": "<choice><abbr>enl<am>\u0304</am></abbr><expan>en<ex>e</ex>l</expan></choice>", "expanded": "enlenel", "index": "110", "rule_match": ["enlenel", "enl\u0304enl", "<choice><abbr>enl<am>\u0304</am></abbr><expan>en<ex>e</ex>l</expan></choice>"], "reading": "E2", "t": "enl\u0304enl"}, {"original": "castiello", "index": "112", "rule_match": ["castiello"], "reading": "E2", "t": "castiello"}], "id": "E2"}], "apparatus": [{"end": 1, "first_word_index": "1.1", "readings": [{"_id": "aa06cf762f88d4dcf394704746540457", "suffixes": [""], "text": [], "witnesses": ["E2"], "type": "om", "label": "a"}, {"_id": "1fa434471bea920fb4cb93f42124898f", "witnesses": ["D", "S", "Ss"], "text": [{"interface": "e", "D": {"original": "E", "index": "2", "rule_match": ["E", "e"], "pc_before": "\u00b6&nbsp;", "t": "E"}, "Ss": {"original": "\u204a", "fullxml": "<am>\u204a</am><ex>e</ex>", "expanded": "e", "index": "2", "rule_match": ["e", "\u204a", "<am>\u204a</am><ex>e</ex>"], "t": "\u204a"}, "index": "1.1", "S": {"original": "\u204a", "fullxml": "<am>\u204a</am><ex>e</ex>", "expanded": "e", "index": "2", "rule_match": ["e", "\u204a", "<am>\u204a</am><ex>e</ex>"], "t": "\u204a"}, "reading": ["D", "S", "Ss"]}], "suffixes": ["", "", ""], "label": "b"}, {"_id": "c88c1f07cd7f217f4c168d34db8de8a3", "standoff_subreadings": ["F"], "details": "lac", "text": [], "created": true, "suffixes": [""], "SR_text": {"F": {"details": "lac verse", "text": [], "type": "lac_verse"}}, "witnesses": ["F"], "type": "lac", "label": "zz"}], "start": 1, "_id": "900b0858d6eedebeca7c1680fa687098"}, {"end": 4, "first_word_index": "2", "readings": [{"_id": "73a3339bb66246dbc633318d1b410bed", "witnesses": ["D", "E2", "S", "Ss"], "text": [{"interface": "el", "D": {"original": "el", "index": "4", "rule_match": ["el"], "t": "el"}, "E2": {"original": "el", "index": "2", "rule_match": ["el"], "pc_before": "\u00b6&nbsp;", "t": "el"}, "Ss": {"original": "el", "index": "4", "rule_match": ["el"], "t": "el"}, "index": "2", "S": {"original": "el", "index": "4", "rule_match": ["el"], "t": "el"}, "reading": ["D", "E2", "S", "Ss"]}, {"interface": "primero", "D": {"original": "p\u2071mero", "fullxml": "p<am>\u2071</am><ex>ri</ex>mero", "expanded": "primero", "index": "6", "rule_match": ["primero", "p\u2071mero", "p<am>\u2071</am><ex>ri</ex>mero"], "t": "p\u2071mero"}, "E2": {"original": "primero", "index": "4", "rule_match": ["primero"], "t": "primero"}, "Ss": {"original": "p\u2071mero", "fullxml": "p<am>\u2071</am><ex>ri</ex>mero", "expanded": "primero", "index": "6", "rule_match": ["primero", "p\u2071mero", "p<am>\u2071</am><ex>ri</ex>mero"], "t": "p\u2071mero"}, "index": "4", "S": {"original": "primero", "index": "6", "rule_match": ["primero"], "t": "primero"}, "reading": ["D", "E2", "S", "Ss"]}], "suffixes": ["", "", "", ""], "label": "a"}, {"_id": "38ae76eef566aa547b09f08114599f3a", "standoff_subreadings": ["F"], "details": "lac", "text": [], "created": true, "suffixes": [""], "SR_text": {"F": {"details": "lac verse", "text": [], "type": "lac_verse"}}, "witnesses": ["F"], "type": "lac", "label": "zz"}], "start": 2, "_id": "762efbafd7c20e5190b7f449b2e61a68"}, {"end": 8, "first_word_index": "6.1", "readings": [{"_id": "c0da48e913ce2a9b577648336654e8ad", "standoff_subreadings": ["D", "S", "Ss"], "text": [{"interface": "que", "index": "6.1", "E2": {"original": "q\u0304", "fullxml": "q<am>\u0304</am><ex>ue</ex>", "expanded": "que", "index": "6", "rule_match": ["que", "q\u0304", "q<am>\u0304</am><ex>ue</ex>"], "t": "q\u0304"}, "reading": ["E2"]}, {"interface": "lo", "index": "8.1", "E2": {"original": "lo", "index": "8", "rule_match": ["lo"], "t": "lo"}, "reading": ["E2"]}], "SR_text": {"Ss": {"text": [{"interface": "quelo", "index": "6.1", "reading": ["Ss"], "Ss": {"original": "quelo", "index": "8", "rule_match": ["quelo"], "interface": "quelo", "t": "quelo"}}]}, "D": {"text": [{"interface": "quelo", "index": "6.1", "reading": ["D"], "D": {"original": "quelo", "index": "8", "rule_match": ["quelo"], "interface": "quelo", "t": "quelo"}}]}, "S": {"text": [{"interface": "quelo", "index": "6.1", "S": {"original": "quelo", "index": "8", "rule_match": ["quelo"], "interface": "quelo", "t": "quelo"}, "reading": ["S"]}]}}, "witnesses": ["D", "E2", "S", "Ss"], "suffixes": ["r", "", "r", "r"], "label": "a"}, {"_id": "db6703ca106089d16fd73f86332bad89", "standoff_subreadings": ["F"], "details": "lac", "text": [], "created": true, "suffixes": [""], "SR_text": {"F": {"details": "lac verse", "text": [], "type": "lac_verse"}}, "witnesses": ["F"], "type": "lac", "label": "zz"}], "start": 6, "_id": "c1b8bb3686b314b65ec8bdb56e66d161"}, {"end": 10, "first_word_index": "10.1", "readings": [{"_id": "ef8719e5ef40006de38f28e305455b8d", "witnesses": ["E2", "S", "Ss"], "text": [{"interface": "cometio", "E2": {"original": "cometio", "index": "10", "rule_match": ["cometio"], "t": "cometio"}, "Ss": {"original": "cometio", "index": "10", "rule_match": ["cometio"], "t": "cometio"}, "index": "10.1", "S": {"original": "cometio", "index": "10", "rule_match": ["cometio"], "t": "cometio"}, "reading": ["E2", "S", "Ss"]}], "suffixes": ["", "", ""], "label": "a"}, {"_id": "fc0c49b020f8b9a086990272ef0c826e", "witnesses": ["D"], "text": [{"interface": "comen\u00e7o", "index": "10.1", "reading": ["D"], "D": {"original": "comen\u00e7o", "index": "10", "rule_match": ["comen\u00e7o"], "t": "comen\u00e7o"}}], "suffixes": [""], "label": "b"}, {"_id": "908056e0c7f77cc19631dc53a55f36f4", "standoff_subreadings": ["F"], "details": "lac", "text": [], "created": true, "suffixes": [""], "SR_text": {"F": {"details": "lac verse", "text": [], "type": "lac_verse"}}, "witnesses": ["F"], "type": "lac", "label": "zz"}], "start": 10, "_id": "94116edf37aed5188794c2eaa6715561"}, {"end": 12, "first_word_index": "12.1", "readings": [{"_id": "668fea9d683750530be8fa07a27abd7a", "witnesses": ["D", "E2", "Ss"], "text": [{"interface": "e", "D": {"original": "\u204a", "fullxml": "<am>\u204a</am><ex>e</ex>", "expanded": "e", "index": "12", "rule_match": ["e", "\u204a", "<am>\u204a</am><ex>e</ex>"], "t": "\u204a"}, "E2": {"original": "\u204a", "fullxml": "<am>\u204a</am><ex>e</ex>", "expanded": "e", "index": "12", "rule_match": ["e", "\u204a", "<am>\u204a</am><ex>e</ex>"], "t": "\u204a"}, "Ss": {"original": "\u204a", "fullxml": "<am>\u204a</am><ex>e</ex>", "expanded": "e", "index": "12", "rule_match": ["e", "\u204a", "<am>\u204a</am><ex>e</ex>"], "t": "\u204a"}, "index": "12.1", "reading": ["D", "E2", "Ss"]}], "suffixes": ["", "", ""], "label": "a"}, {"_id": "a54a89429732b44e62126d26e1262b1f", "suffixes": [""], "text": [], "witnesses": ["S"], "type": "om", "label": "b"}, {"_id": "415f4f691dcea89764840147a8843a4f", "standoff_subreadings": ["F"], "details": "lac", "text": [], "created": true, "suffixes": [""], "SR_text": {"F": {"details": "lac verse", "text": [], "type": "lac_verse"}}, "witnesses": ["F"], "type": "lac", "label": "zz"}], "start": 12, "_id": "f1a54659313c74230a30375635d9c821"}, {"end": 44, "first_word_index": "14", "readings": [{"_id": "7278f9666229cf008633df595c7bb6ee", "witnesses": ["D", "E2", "S", "Ss"], "text": [{"interface": "abrio", "D": {"original": "abrio", "index": "14", "rule_match": ["abrio"], "t": "abrio"}, "E2": {"original": "abrio", "index": "14", "rule_match": ["abrio"], "t": "abrio"}, "Ss": {"original": "abrio", "index": "14", "rule_match": ["abrio"], "t": "abrio"}, "index": "14", "S": {"original": "abrio", "index": "12", "rule_match": ["abrio"], "t": "abrio"}, "reading": ["D", "E2", "S", "Ss"]}, {"interface": "la", "D": {"original": "la", "index": "16", "rule_match": ["la"], "t": "la"}, "E2": {"original": "la", "index": "16", "rule_match": ["la"], "t": "la"}, "Ss": {"original": "la", "index": "16", "rule_match": ["la"], "t": "la"}, "index": "16", "S": {"original": "la", "index": "14", "rule_match": ["la"], "t": "la"}, "reading": ["D", "E2", "S", "Ss"]}, {"interface": "carrera", "D": {"original": "Carrera", "index": "18", "rule_match": ["Carrera", "carrera"], "t": "Carrera"}, "E2": {"original": "carrera", "index": "18", "rule_match": ["carrera"], "t": "carrera"}, "Ss": {"original": "carrera", "index": "18", "rule_match": ["carrera"], "t": "carrera"}, "index": "18", "S": {"original": "carrera", "index": "16", "rule_match": ["carrera"], "t": "carrera"}, "reading": ["D", "E2", "S", "Ss"]}, {"interface": "alos", "D": {"original": "alos", "index": "20", "rule_match": ["alos"], "t": "alos"}, "E2": {"original": "alos", "index": "20", "rule_match": ["alos"], "t": "alos"}, "Ss": {"original": "alos", "index": "20", "rule_match": ["alos"], "t": "alos"}, "index": "20", "S": {"original": "alos", "index": "18", "rule_match": ["alos"], "t": "alos"}, "reading": ["D", "E2", "S", "Ss"]}, {"interface": "otros", "D": {"original": "otros", "index": "22", "rule_match": ["otros"], "t": "otros"}, "E2": {"original": "otros", "index": "22", "rule_match": ["otros"], "t": "otros"}, "Ss": {"original": "otros", "index": "22", "rule_match": ["otros"], "t": "otros"}, "index": "22", "S": {"original": "otros", "index": "20", "rule_match": ["otros"], "t": "otros"}, "reading": ["D", "E2", "S", "Ss"]}, {"interface": "e", "D": {"original": "\u204a", "fullxml": "<am>\u204a</am><ex>e</ex>", "expanded": "e", "index": "24", "rule_match": ["e", "\u204a", "<am>\u204a</am><ex>e</ex>"], "t": "\u204a"}, "E2": {"original": "\u204a", "fullxml": "<am>\u204a</am><ex>e</ex>", "expanded": "e", "index": "24", "rule_match": ["e", "\u204a", "<am>\u204a</am><ex>e</ex>"], "t": "\u204a"}, "Ss": {"original": "\u204a", "fullxml": "<am>\u204a</am><ex>e</ex>", "expanded": "e", "index": "24", "rule_match": ["e", "\u204a", "<am>\u204a</am><ex>e</ex>"], "t": "\u204a"}, "index": "24", "S": {"original": "E", "index": "22", "rule_match": ["E", "e"], "t": "E"}, "reading": ["D", "E2", "S", "Ss"]}, {"interface": "el", "D": {"original": "el", "index": "26", "rule_match": ["el"], "t": "el"}, "E2": {"original": "el", "index": "26", "rule_match": ["el"], "t": "el"}, "Ss": {"original": "el", "index": "26", "rule_match": ["el"], "t": "el"}, "index": "26", "S": {"original": "el", "index": "24", "rule_match": ["el"], "t": "el"}, "reading": ["D", "E2", "S", "Ss"]}, {"interface": "que", "D": {"original": "q\u0304", "fullxml": "q<am>\u0304</am><ex>ue</ex>", "expanded": "que", "index": "28", "rule_match": ["que", "q\u0304", "q<am>\u0304</am><ex>ue</ex>"], "t": "q\u0304"}, "E2": {"original": "q\u0304", "fullxml": "q<am>\u0304</am><ex>ue</ex>", "expanded": "que", "index": "28", "rule_match": ["que", "q\u0304", "q<am>\u0304</am><ex>ue</ex>"], "t": "q\u0304"}, "Ss": {"original": "que", "index": "28", "rule_match": ["que"], "t": "que"}, "index": "28", "S": {"original": "que", "index": "26", "rule_match": ["que"], "t": "que"}, "reading": ["D", "E2", "S", "Ss"]}, {"interface": "ante", "D": {"original": "ante", "index": "30", "rule_match": ["ante"], "t": "ante"}, "E2": {"original": "ante", "index": "30", "rule_match": ["ante"], "t": "ante"}, "Ss": {"original": "ante", "index": "30", "rule_match": ["ante"], "t": "ante"}, "index": "30", "S": {"original": "ante", "index": "28", "rule_match": ["ante"], "t": "ante"}, "reading": ["D", "E2", "S", "Ss"]}, {"interface": "subio", "D": {"original": "subio", "index": "32", "rule_match": ["subio"], "t": "subio"}, "E2": {"original": "subio", "index": "32", "rule_match": ["subio"], "t": "subio"}, "Ss": {"original": "subio", "index": "32", "rule_match": ["subio"], "t": "subio"}, "index": "32", "S": {"original": "subio", "index": "30", "rule_match": ["subio"], "t": "subio"}, "reading": ["D", "E2", "S", "Ss"]}, {"interface": "por", "D": {"original": "por", "index": "34", "rule_match": ["por"], "t": "por"}, "E2": {"original": "por", "index": "34", "rule_match": ["por"], "t": "por"}, "Ss": {"original": "por", "index": "34", "rule_match": ["por"], "t": "por"}, "index": "34", "S": {"original": "por", "index": "32", "rule_match": ["por"], "t": "por"}, "reading": ["D", "E2", "S", "Ss"]}, {"interface": "la", "D": {"original": "la", "index": "36", "rule_match": ["la"], "t": "la"}, "E2": {"original": "la", "index": "36", "rule_match": ["la"], "t": "la"}, "Ss": {"original": "la", "index": "36", "rule_match": ["la"], "t": "la"}, "index": "36", "S": {"original": "la", "index": "34", "rule_match": ["la"], "t": "la"}, "reading": ["D", "E2", "S", "Ss"]}, {"interface": "penna", "D": {"original": "pen\u0304a", "fullxml": "pen<am>\u0304</am><ex>n</ex>a", "expanded": "penna", "index": "38", "rule_match": ["penna", "pen\u0304a", "pen<am>\u0304</am><ex>n</ex>a"], "t": "pen\u0304a"}, "E2": {"original": "pen\u0304a", "fullxml": "pen<am>\u0304</am><ex>n</ex>a", "expanded": "penna", "index": "38", "rule_match": ["penna", "pen\u0304a", "pen<am>\u0304</am><ex>n</ex>a"], "t": "pen\u0304a"}, "Ss": {"original": "pen\u0304a", "fullxml": "pen<am>\u0304</am><ex>n</ex>a", "expanded": "penna", "index": "38", "rule_match": ["penna", "pen\u0304a", "pen<am>\u0304</am><ex>n</ex>a"], "t": "pen\u0304a"}, "index": "38", "S": {"original": "pen\u0304a", "fullxml": "pen<am>\u0304</am><ex>n</ex>a", "expanded": "penna", "index": "36", "rule_match": ["penna", "pen\u0304a", "pen<am>\u0304</am><ex>n</ex>a"], "t": "pen\u0304a"}, "reading": ["D", "E2", "S", "Ss"]}, {"interface": "arriba", "D": {"original": "arriba", "index": "40", "rule_match": ["arriba"], "t": "arriba"}, "E2": {"original": "arriba", "index": "40", "rule_match": ["arriba"], "t": "arriba"}, "Ss": {"original": "arriba", "index": "40", "rule_match": ["arriba"], "t": "arriba"}, "index": "40", "S": {"original": "arriba", "index": "38", "rule_match": ["arriba"], "t": "arriba"}, "reading": ["D", "E2", "S", "Ss"]}, {"interface": "fue", "D": {"original": "fue", "index": "42", "rule_match": ["fue"], "t": "fue"}, "E2": {"original": "fue", "index": "42", "rule_match": ["fue"], "t": "fue"}, "Ss": {"original": "fue", "index": "42", "rule_match": ["fue"], "t": "fue"}, "index": "42", "S": {"original": "fue", "index": "40", "rule_match": ["fue"], "t": "fue"}, "reading": ["D", "E2", "S", "Ss"]}, {"interface": "diego", "D": {"original": "diego", "index": "44", "rule_match": ["diego"], "t": "diego"}, "E2": {"original": "diego", "index": "44", "rule_match": ["diego"], "t": "diego"}, "Ss": {"original": "diego", "index": "44", "rule_match": ["diego"], "t": "diego"}, "index": "44", "S": {"original": "diego", "index": "42", "rule_match": ["diego"], "t": "diego"}, "reading": ["D", "E2", "S", "Ss"]}], "suffixes": ["", "", "", ""], "label": "a"}, {"_id": "d2f4fd34766a5e309ff5c15fca09d0e0", "standoff_subreadings": ["F"], "details": "lac", "text": [], "created": true, "suffixes": [""], "SR_text": {"F": {"details": "lac verse", "text": [], "type": "lac_verse"}}, "witnesses": ["F"], "type": "lac", "label": "zz"}], "start": 14, "_id": "e14e8ccf36c4f583af7fd13973468f16"}, {"end": 46, "first_word_index": "46.1", "readings": [{"_id": "b3bbd423d7965ed5b4ced139571d39f2", "witnesses": ["D", "E2", "S"], "text": [{"interface": "perez", "D": {"original": "\ua751z", "fullxml": "<am>\ua751</am><ex>pere</ex>z", "expanded": "perez", "index": "46", "rule_match": ["perez", "\ua751z", "<am>\ua751</am><ex>pere</ex>z"], "t": "\ua751z"}, "E2": {"original": "perez", "index": "46", "rule_match": ["perez"], "t": "perez"}, "index": "46.1", "S": {"original": "perez", "index": "44", "rule_match": ["perez"], "t": "perez"}, "reading": ["D", "E2", "S"]}], "suffixes": ["", "", ""], "label": "a"}, {"_id": "fc5fb00eb72dde937b541bf6e9e2a898", "witnesses": ["Ss"], "text": [{"Ss": {"original": "peres", "index": "46", "rule_match": ["peres"], "t": "peres"}, "index": "46.1", "interface": "peres", "reading": ["Ss"]}], "suffixes": [""], "label": "b"}, {"_id": "f38bce1d56924bbaf382d7c491c984ee", "standoff_subreadings": ["F"], "details": "lac", "text": [], "created": true, "suffixes": [""], "SR_text": {"F": {"details": "lac verse", "text": [], "type": "lac_verse"}}, "witnesses": ["F"], "type": "lac", "label": "zz"}], "start": 46, "_id": "2b81b9bec1ffafa1fcc4d185d2bfdf0f"}, {"end": 52, "first_word_index": "48", "readings": [{"_id": "2404d9836290e4b1903de75855cb4b52", "witnesses": ["D", "E2", "S", "Ss"], "text": [{"interface": "machuca", "D": {"original": "machuca", "index": "48", "rule_match": ["machuca"], "t": "machuca"}, "E2": {"original": "machuca", "index": "48", "rule_match": ["machuca"], "t": "machuca"}, "Ss": {"original": "machuca", "index": "48", "rule_match": ["machuca"], "t": "machuca"}, "index": "48", "S": {"original": "machuca", "index": "46", "rule_match": ["machuca"], "t": "machuca"}, "reading": ["D", "E2", "S", "Ss"]}, {"interface": "e", "D": {"original": "\u204a", "fullxml": "<am>\u204a</am><ex>e</ex>", "expanded": "e", "index": "50", "rule_match": ["e", "\u204a", "<am>\u204a</am><ex>e</ex>"], "t": "\u204a"}, "E2": {"original": "\u204a", "fullxml": "<am>\u204a</am><ex>e</ex>", "expanded": "e", "index": "50", "rule_match": ["e", "\u204a", "<am>\u204a</am><ex>e</ex>"], "t": "\u204a"}, "Ss": {"original": "\u204a", "fullxml": "<am>\u204a</am><ex>e</ex>", "expanded": "e", "index": "50", "rule_match": ["e", "\u204a", "<am>\u204a</am><ex>e</ex>"], "t": "\u204a"}, "index": "50", "S": {"original": "\u204a", "fullxml": "<am>\u204a</am><ex>e</ex>", "expanded": "e", "index": "48", "rule_match": ["e", "\u204a", "<am>\u204a</am><ex>e</ex>"], "t": "\u204a"}, "reading": ["D", "E2", "S", "Ss"]}, {"interface": "murieron", "D": {"original": "muriero\u0304", "fullxml": "muriero<am>\u0304</am><ex>n</ex>", "expanded": "murieron", "index": "52", "rule_match": ["murieron", "muriero\u0304", "muriero<am>\u0304</am><ex>n</ex>"], "t": "muriero\u0304"}, "E2": {"original": "murieron", "index": "52", "rule_match": ["murieron"], "t": "murieron"}, "Ss": {"original": "murieron", "index": "52", "rule_match": ["murieron"], "t": "murieron"}, "index": "52", "S": {"original": "murieron", "index": "50", "rule_match": ["murieron"], "t": "murieron"}, "reading": ["D", "E2", "S", "Ss"]}], "suffixes": ["", "", "", ""], "label": "a"}, {"_id": "60affb5c24a88c4e76aeb494c9f9e7d6", "standoff_subreadings": ["F"], "details": "lac", "text": [], "created": true, "suffixes": [""], "SR_text": {"F": {"details": "lac verse", "text": [], "type": "lac_verse"}}, "witnesses": ["F"], "type": "lac", "label": "zz"}], "start": 48, "_id": "9986ab3b57942b27990856e8c0058c16"}, {"end": 54, "first_word_index": "54.1", "readings": [{"_id": "2ebf7cfb7188d7dde9f9c97c5ced1525", "witnesses": ["D", "E2", "S", "Ss"], "text": [{"interface": "y", "D": {"original": "y", "index": "54", "rule_match": ["y"], "t": "y"}, "E2": {"original": "y", "index": "54", "rule_match": ["y"], "t": "y"}, "Ss": {"original": "y", "index": "54", "rule_match": ["y"], "t": "y"}, "index": "54.1", "S": {"original": "y", "index": "52", "rule_match": ["y"], "t": "y"}, "reading": ["D", "E2", "S", "Ss"]}], "suffixes": ["", "", "", ""], "label": "a"}, {"_id": "1a9f87f1c5d568f947e79f5f5f66ac83", "standoff_subreadings": ["F"], "details": "lac", "text": [], "created": true, "suffixes": [""], "SR_text": {"F": {"details": "lac verse", "text": [], "type": "lac_verse"}}, "witnesses": ["F"], "type": "lac", "label": "zz"}], "start": 54, "_id": "dbdd0cdd5fce3cda9eff784b05ccdd0f"}, {"end": 58, "first_word_index": "56.1", "readings": [{"_id": "6c328fcd2a70a1350fd3cc1c1174de67", "witnesses": ["D", "E2", "S"], "text": [{"interface": "de", "D": {"original": "de", "index": "56", "rule_match": ["de"], "t": "de"}, "E2": {"original": "de", "index": "56", "rule_match": ["de"], "t": "de"}, "index": "56.1", "S": {"original": "de", "index": "54", "rule_match": ["de"], "t": "de"}, "reading": ["E2", "D", "S"]}, {"interface": "aqueellos", "D": {"original": "aq\u0304llos", "n": "aqueellos", "fullxml": "aq<am>\u0304</am><ex>ue</ex>llos", "decision_details": [{"scope": "once", "_id": "verse_CPSF:entity=1065:block=2400_124e25e8-3575-4e36-be82-ccd408143a7b", "n": "aqueellos", "t": "aquellos", "class": "none"}], "expanded": "aquellos", "decision_class": ["none"], "index": "58", "rule_match": ["aquellos", "aq\u0304llos", "aq<am>\u0304</am><ex>ue</ex>llos"], "t": "aq\u0304llos"}, "E2": {"original": "aqu\u0304ellos", "fullxml": "aqu<am>\u0304</am><ex>e</ex>ellos", "expanded": "aqueellos", "index": "58", "rule_match": ["aqueellos", "aqu\u0304ellos", "aqu<am>\u0304</am><ex>e</ex>ellos"], "t": "aqu\u0304ellos"}, "index": "58.1", "S": {"original": "aq\u0304llos", "n": "aqueellos", "fullxml": "aq<am>\u0304</am><ex>ue</ex>llos", "decision_details": [{"scope": "once", "_id": "verse_CPSF:entity=1065:block=2400_2ab3614e-23f5-437c-a94f-810ea630087f", "n": "aqueellos", "t": "aquellos", "class": "none"}], "expanded": "aquellos", "decision_class": ["none"], "index": "56", "rule_match": ["aquellos", "aq\u0304llos", "aq<am>\u0304</am><ex>ue</ex>llos"], "t": "aq\u0304llos"}, "reading": ["E2", "D", "S"]}], "suffixes": ["", "", ""], "label": "a"}, {"_id": "7f65b089feab34c2daf9f7702aebad63", "witnesses": ["Ss"], "text": [{"interface": "delos", "index": "58.1", "reading": ["Ss"], "Ss": {"original": "delos", "index": "56", "fullxml": "delo<hi&nbsp;rend=''sup''>s</hi>", "rule_match": ["delos", "delo<hi rend=''sup''>s</hi>"], "t": "delos"}}], "suffixes": [""], "label": "b"}, {"_id": "a095018288b2a6fe149730c705029109", "standoff_subreadings": ["F"], "details": "lac", "text": [], "created": true, "suffixes": [""], "SR_text": {"F": {"details": "lac verse", "text": [], "type": "lac_verse"}}, "witnesses": ["F"], "type": "lac", "label": "zz"}], "start": 56, "_id": "34844b33976132c3eb7b35698a650da0"}, {"end": 70, "first_word_index": "60", "readings": [{"_id": "2985fa751439f44cbe0d4748b7a858f1", "witnesses": ["D", "E2", "S", "Ss"], "text": [{"interface": "quarenta", "D": {"original": "quarenta", "index": "60", "rule_match": ["quarenta"], "t": "quarenta"}, "E2": {"original": "q\u1d45renta", "fullxml": "q<am>\u1d45</am><ex>ua</ex>renta", "expanded": "quarenta", "index": "60", "rule_match": ["quarenta", "q\u1d45renta", "q<am>\u1d45</am><ex>ua</ex>renta"], "t": "q\u1d45renta"}, "Ss": {"original": "quarenta", "index": "58", "rule_match": ["quarenta"], "t": "quarenta"}, "index": "60", "S": {"original": "quarenta", "index": "58", "rule_match": ["quarenta"], "t": "quarenta"}, "reading": ["E2", "D", "S", "Ss"]}, {"interface": "e", "D": {"original": "\u204a", "fullxml": "<am>\u204a</am><ex>e</ex>", "expanded": "e", "index": "62", "rule_match": ["e", "\u204a", "<am>\u204a</am><ex>e</ex>"], "t": "\u204a"}, "E2": {"original": "\u204a", "fullxml": "<am>\u204a</am><ex>e</ex>", "expanded": "e", "index": "62", "rule_match": ["e", "\u204a", "<am>\u204a</am><ex>e</ex>"], "t": "\u204a"}, "Ss": {"original": "\u204a", "fullxml": "<am>\u204a</am><ex>e</ex>", "expanded": "e", "index": "60", "rule_match": ["e", "\u204a", "<am>\u204a</am><ex>e</ex>"], "t": "\u204a"}, "index": "62", "S": {"original": "\u204a", "fullxml": "<am>\u204a</am><ex>e</ex>", "expanded": "e", "index": "60", "rule_match": ["e", "\u204a", "<am>\u204a</am><ex>e</ex>"], "t": "\u204a"}, "reading": ["E2", "D", "S", "Ss"]}, {"interface": "cinco", "D": {"original": "\u00e7inco", "n": "cinco", "decision_details": [{"scope": "once", "_id": "verse_CPSF:entity=1065:block=2400_9591cac7-83c4-4005-86c7-20bfbf160d7c", "n": "cinco", "t": "\u00e7inco", "class": "none"}], "decision_class": ["none"], "index": "64", "rule_match": ["\u00e7inco"], "t": "\u00e7inco"}, "E2": {"original": "ci\u0304co", "fullxml": "ci<am>\u0304</am><ex>n</ex>co", "expanded": "cinco", "index": "64", "rule_match": ["cinco", "ci\u0304co", "ci<am>\u0304</am><ex>n</ex>co"], "t": "ci\u0304co"}, "Ss": {"original": "\u00e7inco", "n": "cinco", "decision_details": [{"scope": "once", "_id": "verse_CPSF:entity=1065:block=2400_3cc2dfb7-1c0f-4975-8d72-a70a607c3d72", "n": "cinco", "t": "\u00e7inco", "class": "none"}], "decision_class": ["none"], "index": "62", "rule_match": ["\u00e7inco"], "t": "\u00e7inco"}, "index": "64", "S": {"original": "\u00e7inco", "n": "cinco", "decision_details": [{"scope": "once", "_id": "verse_CPSF:entity=1065:block=2400_7674e3ed-73fa-46dc-af51-9925e0a8cd63", "n": "cinco", "t": "\u00e7inco", "class": "none"}], "decision_class": ["none"], "index": "62", "rule_match": ["\u00e7inco"], "t": "\u00e7inco"}, "reading": ["E2", "D", "S", "Ss"]}, {"interface": "caualleros", "D": {"original": "caualleros", "index": "66", "rule_match": ["caualleros"], "t": "caualleros"}, "E2": {"original": "caualleros", "index": "66", "rule_match": ["caualleros"], "t": "caualleros"}, "Ss": {"original": "caualleros", "index": "64", "rule_match": ["caualleros"], "t": "caualleros"}, "index": "66", "S": {"original": "caualleros", "index": "64", "rule_match": ["caualleros"], "t": "caualleros"}, "reading": ["E2", "D", "S", "Ss"]}, {"interface": "los", "D": {"original": "los", "index": "68", "rule_match": ["los"], "t": "los"}, "E2": {"original": "los", "index": "68", "rule_match": ["los"], "t": "los"}, "Ss": {"original": "los", "index": "66", "rule_match": ["los"], "t": "los"}, "index": "68", "S": {"original": "los", "index": "66", "rule_match": ["los"], "t": "los"}, "reading": ["E2", "D", "S", "Ss"]}, {"interface": "que", "D": {"original": "q\u0304", "fullxml": "q<am>\u0304</am><ex>ue</ex>", "expanded": "que", "index": "70", "rule_match": ["que", "q\u0304", "q<am>\u0304</am><ex>ue</ex>"], "t": "q\u0304"}, "E2": {"original": "q\u0304", "fullxml": "q<am>\u0304</am><ex>ue</ex>", "expanded": "que", "index": "70", "rule_match": ["que", "q\u0304", "q<am>\u0304</am><ex>ue</ex>"], "t": "q\u0304"}, "Ss": {"original": "q\u0304", "fullxml": "q<am>\u0304</am><ex>ue</ex>", "expanded": "que", "index": "68", "rule_match": ["que", "q\u0304", "q<am>\u0304</am><ex>ue</ex>"], "t": "q\u0304"}, "index": "70", "S": {"original": "que", "index": "68", "rule_match": ["que"], "t": "que"}, "reading": ["E2", "D", "S", "Ss"]}], "suffixes": ["", "", "", ""], "label": "a"}, {"_id": "469434aa849c45f377c1f09cd09b3290", "standoff_subreadings": ["F"], "details": "lac", "text": [], "created": true, "suffixes": [""], "SR_text": {"F": {"details": "lac verse", "text": [], "type": "lac_verse"}}, "witnesses": ["F"], "type": "lac", "label": "zz"}], "start": 60, "_id": "862d62df95aed79e23a25c61a937796d"}, {"end": 72, "first_word_index": "72.1", "readings": [{"_id": "721e91666c3c215e8f0b9783cf4f864e", "witnesses": ["E2", "S"], "text": [{"interface": "destaiaron", "index": "72.1", "E2": {"original": "destaiaron", "index": "72", "rule_match": ["destaiaron"], "t": "destaiaron"}, "S": {"original": "destajaron", "n": "destaiaron", "decision_details": [{"scope": "once", "_id": "verse_CPSF:entity=1065:block=2400_1932ca76-991a-4ba7-a36c-bd624fbb777d", "n": "destaiaron", "t": "destajaron", "class": "none"}], "decision_class": ["none"], "index": "70", "rule_match": ["destajaron"], "t": "destajaron"}, "reading": ["E2", "S"]}], "suffixes": ["", ""], "label": "a"}, {"_id": "c520bbde64016e8a68453941defa2e90", "witnesses": ["Ss"], "text": [{"Ss": {"original": "atajaron", "index": "70", "rule_match": ["atajaron"], "t": "atajaron"}, "index": "72.1", "interface": "atajaron", "reading": ["Ss"]}], "suffixes": [""], "label": "b"}, {"_id": "d6dde2c9b4fd80ab57d365166de4ab6f", "witnesses": ["D"], "text": [{"interface": "destajaroue", "index": "72.1", "reading": ["D"], "D": {"original": "destajaro\u0304", "fullxml": "destajaro<am>\u0304</am><ex>ue</ex>", "expanded": "destajaroue", "index": "72", "rule_match": ["destajaroue", "destajaro\u0304", "destajaro<am>\u0304</am><ex>ue</ex>"], "t": "destajaro\u0304"}}], "suffixes": [""], "label": "c"}, {"_id": "d1ca83bfef4c1fcbb164530b103ff24c", "standoff_subreadings": ["F"], "details": "lac", "text": [], "created": true, "suffixes": [""], "SR_text": {"F": {"details": "lac verse", "text": [], "type": "lac_verse"}}, "witnesses": ["F"], "type": "lac", "label": "zz"}], "start": 72, "_id": "78c826149be483896e47929644623c4f"}, {"end": 80, "first_word_index": "74.1", "readings": [{"_id": "3ee74905e0ef9e4925a9cd445d3e7053", "witnesses": ["D", "E2", "S", "Ss"], "text": [{"interface": "los", "D": {"original": "los", "index": "74", "rule_match": ["los"], "t": "los"}, "E2": {"original": "los", "index": "74", "rule_match": ["los"], "t": "los"}, "Ss": {"original": "los", "index": "72", "rule_match": ["los"], "t": "los"}, "index": "74.1", "S": {"original": "los", "index": "72", "rule_match": ["los"], "t": "los"}, "reading": ["Ss", "E2", "D", "S"]}, {"interface": "moros", "D": {"original": "moros", "index": "76", "rule_match": ["moros"], "t": "moros"}, "E2": {"original": "moros", "index": "76", "rule_match": ["moros"], "t": "moros"}, "Ss": {"original": "moros", "index": "74", "rule_match": ["moros"], "t": "moros"}, "index": "76.1", "S": {"original": "moros", "index": "74", "rule_match": ["moros"], "t": "moros"}, "reading": ["Ss", "E2", "D", "S"]}, {"interface": "que", "D": {"original": "q\u0304", "fullxml": "q<am>\u0304</am><ex>ue</ex>", "expanded": "que", "index": "78", "rule_match": ["que", "q\u0304", "q<am>\u0304</am><ex>ue</ex>"], "t": "q\u0304"}, "E2": {"original": "que", "index": "78", "rule_match": ["que"], "t": "que"}, "Ss": {"original": "que", "index": "76", "rule_match": ["que"], "t": "que"}, "index": "78.1", "S": {"original": "que", "index": "76", "rule_match": ["que"], "t": "que"}, "reading": ["Ss", "E2", "D", "S"]}, {"interface": "non", "D": {"original": "no\u0304", "fullxml": "no<am>\u0304</am><ex>n</ex>", "expanded": "non", "index": "80", "rule_match": ["non", "no\u0304", "no<am>\u0304</am><ex>n</ex>"], "t": "no\u0304"}, "E2": {"original": "non", "index": "80", "rule_match": ["non"], "t": "non"}, "Ss": {"original": "non", "index": "78", "rule_match": ["non"], "t": "non"}, "index": "80.1", "S": {"original": "non", "index": "78", "rule_match": ["non"], "t": "non"}, "reading": ["Ss", "E2", "D", "S"]}], "suffixes": ["", "", "", ""], "label": "a"}, {"_id": "6b559625dd92e9e2e5ac1aa09594b93f", "standoff_subreadings": ["F"], "details": "lac", "text": [], "created": true, "suffixes": [""], "SR_text": {"F": {"details": "lac verse", "text": [], "type": "lac_verse"}}, "witnesses": ["F"], "type": "lac", "label": "zz"}], "start": 74, "_id": "f5ab8d5c344c3caba2310508674e4599"}, {"end": 82, "first_word_index": "82.1", "readings": [{"_id": "3e0d6fe82d33a2a51062a37b484d1582", "witnesses": ["E2", "Ss"], "text": [{"Ss": {"original": "podieron", "index": "80", "rule_match": ["podieron"], "t": "podieron"}, "index": "82.1", "E2": {"original": "podieron", "index": "82", "rule_match": ["podieron"], "t": "podieron"}, "interface": "podieron", "reading": ["Ss", "E2"]}], "suffixes": ["", ""], "label": "a"}, {"_id": "406fdfe20b3301a9f77333e2d6da9f57", "witnesses": ["D", "S"], "text": [{"interface": "pudieron", "index": "82.1", "S": {"original": "pudieron", "index": "80", "rule_match": ["pudieron"], "t": "pudieron"}, "reading": ["D", "S"], "D": {"original": "pudiero\u0304", "fullxml": "pudiero<am>\u0304</am><ex>n</ex>", "expanded": "pudieron", "index": "82", "rule_match": ["pudieron", "pudiero\u0304", "pudiero<am>\u0304</am><ex>n</ex>"], "t": "pudiero\u0304"}}], "suffixes": ["", ""], "label": "b"}, {"_id": "da2028d4d59539869e81cee353213d3b", "standoff_subreadings": ["F"], "details": "lac", "text": [], "created": true, "suffixes": [""], "SR_text": {"F": {"details": "lac verse", "text": [], "type": "lac_verse"}}, "witnesses": ["F"], "type": "lac", "label": "zz"}], "start": 82, "_id": "f0b6604f0dc9538a28b3621d7b77d941"}, {"end": 94, "first_word_index": "84.1", "readings": [{"_id": "6acf1076adb711cd0ae005b8ca6f7af2", "witnesses": ["D", "E2", "S", "Ss"], "text": [{"interface": "pasar", "D": {"original": "pasar", "index": "84", "rule_match": ["pasar"], "t": "pasar"}, "E2": {"original": "pasar", "index": "84", "rule_match": ["pasar"], "t": "pasar"}, "Ss": {"original": "pasar", "index": "82", "pc_after": ".", "rule_match": ["pasar"], "t": "pasar"}, "index": "84.1", "S": {"original": "pasar", "index": "82", "rule_match": ["pasar"], "t": "pasar"}, "reading": ["Ss", "E2", "D", "S"]}, {"interface": "e", "D": {"original": "\u204a", "fullxml": "<am>\u204a</am><ex>e</ex>", "expanded": "e", "index": "86", "rule_match": ["e", "\u204a", "<am>\u204a</am><ex>e</ex>"], "t": "\u204a"}, "E2": {"original": "\u204a", "fullxml": "<am>\u204a</am><ex>e</ex>", "expanded": "e", "index": "86", "rule_match": ["e", "\u204a", "<am>\u204a</am><ex>e</ex>"], "t": "\u204a"}, "Ss": {"original": "E", "index": "84", "rule_match": ["E", "e"], "t": "E"}, "index": "86.1", "S": {"original": "\u204a", "fullxml": "<am>\u204a</am><ex>e</ex>", "expanded": "e", "index": "84", "rule_match": ["e", "\u204a", "<am>\u204a</am><ex>e</ex>"], "t": "\u204a"}, "reading": ["Ss", "E2", "D", "S"]}, {"interface": "los", "D": {"original": "los", "index": "88", "rule_match": ["los"], "t": "los"}, "E2": {"original": "los", "index": "88", "rule_match": ["los"], "t": "los"}, "Ss": {"original": "los", "index": "86", "rule_match": ["los"], "t": "los"}, "index": "88.1", "S": {"original": "los", "index": "86", "rule_match": ["los"], "t": "los"}, "reading": ["Ss", "E2", "D", "S"]}, {"interface": "otros", "D": {"original": "otros", "index": "90", "rule_match": ["otros"], "t": "otros"}, "E2": {"original": "otros", "index": "90", "rule_match": ["otros"], "t": "otros"}, "Ss": {"original": "otros", "index": "88", "rule_match": ["otros"], "t": "otros"}, "index": "90.1", "S": {"original": "otros", "index": "88", "rule_match": ["otros"], "t": "otros"}, "reading": ["Ss", "E2", "D", "S"]}, {"interface": "pasaron", "D": {"original": "pasaron", "index": "92", "rule_match": ["pasaron"], "t": "pasaron"}, "E2": {"original": "pasaron", "index": "92", "rule_match": ["pasaron"], "t": "pasaron"}, "Ss": {"original": "pasaro\u0304", "fullxml": "pasaro<am>\u0304</am><ex>n</ex>", "expanded": "pasaron", "index": "90", "rule_match": ["pasaron", "pasaro\u0304", "pasaro<am>\u0304</am><ex>n</ex>"], "t": "pasaro\u0304"}, "index": "92.1", "S": {"original": "pasaron", "index": "90", "rule_match": ["pasaron"], "t": "pasaron"}, "reading": ["Ss", "E2", "D", "S"]}, {"interface": "e", "D": {"original": "\u204a", "fullxml": "<am>\u204a</am><ex>e</ex>", "expanded": "e", "index": "94", "rule_match": ["e", "\u204a", "<am>\u204a</am><ex>e</ex>"], "t": "\u204a"}, "E2": {"original": "\u204a", "fullxml": "<am>\u204a</am><ex>e</ex>", "expanded": "e", "index": "94", "rule_match": ["e", "\u204a", "<am>\u204a</am><ex>e</ex>"], "t": "\u204a"}, "Ss": {"original": "\u204a", "fullxml": "<am>\u204a</am><ex>e</ex>", "expanded": "e", "index": "92", "rule_match": ["e", "\u204a", "<am>\u204a</am><ex>e</ex>"], "t": "\u204a"}, "index": "94.1", "S": {"original": "\u204a", "fullxml": "<am>\u204a</am><ex>e</ex>", "expanded": "e", "index": "92", "rule_match": ["e", "\u204a", "<am>\u204a</am><ex>e</ex>"], "t": "\u204a"}, "reading": ["Ss", "E2", "D", "S"]}], "suffixes": ["", "", "", ""], "label": "a"}, {"_id": "c2de58085a77dcc9dfe1ba479b9fff96", "standoff_subreadings": ["F"], "details": "lac", "text": [], "created": true, "suffixes": [""], "SR_text": {"F": {"details": "lac verse", "text": [], "type": "lac_verse"}}, "witnesses": ["F"], "type": "lac", "label": "zz"}], "start": 84, "_id": "809014ef6697f1f33ac4da30f78e452b"}, {"end": 96, "first_word_index": "96.1", "readings": [{"_id": "35cd9d0222adcb27586f8b9637a38c5d", "witnesses": ["E2"], "text": [{"interface": "sobieron", "index": "96.1", "E2": {"original": "sobieron", "index": "96", "rule_match": ["sobieron"], "t": "sobieron"}, "reading": ["E2"]}], "suffixes": [""], "label": "a"}, {"_id": "16c68bc83b1e93a6d7e98020cacf0203", "witnesses": ["D", "S", "Ss"], "text": [{"interface": "subieron", "D": {"original": "subiero\u0304", "fullxml": "subiero<am>\u0304</am><ex>n</ex>", "expanded": "subieron", "index": "96", "rule_match": ["subieron", "subiero\u0304", "subiero<am>\u0304</am><ex>n</ex>"], "t": "subiero\u0304"}, "Ss": {"original": "subieron", "index": "94", "rule_match": ["subieron"], "t": "subieron"}, "index": "96.1", "S": {"original": "subieron", "index": "94", "rule_match": ["subieron"], "t": "subieron"}, "reading": ["Ss", "D", "S"]}], "suffixes": ["", "", ""], "label": "b"}, {"_id": "036056041ae9d642d99fc47a4c953243", "standoff_subreadings": ["F"], "details": "lac", "text": [], "created": true, "suffixes": [""], "SR_text": {"F": {"details": "lac verse", "text": [], "type": "lac_verse"}}, "witnesses": ["F"], "type": "lac", "label": "zz"}], "start": 96, "_id": "314fb4d9469898bb8155840814986e92"}, {"end": 110, "first_word_index": "98.1", "readings": [{"_id": "6640ff2342906113fe5f26f7ff9e2e2d", "witnesses": ["D", "E2", "S", "Ss"], "text": [{"interface": "por", "D": {"original": "por", "index": "98", "rule_match": ["por"], "t": "por"}, "E2": {"original": "por", "index": "98", "rule_match": ["por"], "t": "por"}, "Ss": {"original": "por", "index": "96", "rule_match": ["por"], "t": "por"}, "index": "98.1", "S": {"original": "por", "index": "96", "rule_match": ["por"], "t": "por"}, "reading": ["E2", "Ss", "D", "S"]}, {"interface": "la", "D": {"original": "la", "index": "100", "rule_match": ["la"], "t": "la"}, "E2": {"original": "la", "index": "100", "rule_match": ["la"], "t": "la"}, "Ss": {"original": "la", "index": "98", "rule_match": ["la"], "t": "la"}, "index": "100.1", "S": {"original": "la", "index": "98", "rule_match": ["la"], "t": "la"}, "reading": ["E2", "Ss", "D", "S"]}, {"interface": "penna", "D": {"original": "pen\u0304a", "fullxml": "pen<am>\u0304</am><ex>n</ex>a", "expanded": "penna", "index": "102", "rule_match": ["penna", "pen\u0304a", "pen<am>\u0304</am><ex>n</ex>a"], "t": "pen\u0304a"}, "E2": {"original": "pe\u0304na", "fullxml": "pe<am>\u0304</am><ex>n</ex>na", "expanded": "penna", "index": "102", "rule_match": ["penna", "pe\u0304na", "pe<am>\u0304</am><ex>n</ex>na"], "t": "pe\u0304na"}, "Ss": {"original": "pen\u0304a", "fullxml": "pen<am>\u0304</am><ex>n</ex>a", "expanded": "penna", "index": "100", "rule_match": ["penna", "pen\u0304a", "pen<am>\u0304</am><ex>n</ex>a"], "t": "pen\u0304a"}, "index": "102.1", "S": {"original": "pen\u0304a", "fullxml": "pen<am>\u0304</am><ex>n</ex>a", "expanded": "penna", "index": "100", "rule_match": ["penna", "pen\u0304a", "pen<am>\u0304</am><ex>n</ex>a"], "t": "pen\u0304a"}, "reading": ["E2", "Ss", "D", "S"]}, {"interface": "arriba", "D": {"original": "arriba", "index": "104", "rule_match": ["arriba"], "t": "arriba"}, "E2": {"original": "arriba", "index": "104", "rule_match": ["arriba"], "t": "arriba"}, "Ss": {"original": "arriba", "index": "102", "rule_match": ["arriba"], "t": "arriba"}, "index": "104.1", "S": {"original": "arriba", "index": "102", "rule_match": ["arriba"], "t": "arriba"}, "reading": ["E2", "Ss", "D", "S"]}, {"interface": "e", "D": {"original": "\u204a", "fullxml": "<am>\u204a</am><ex>e</ex>", "expanded": "e", "index": "106", "rule_match": ["e", "\u204a", "<am>\u204a</am><ex>e</ex>"], "t": "\u204a"}, "E2": {"original": "\u204a", "fullxml": "<am>\u204a</am><ex>e</ex>", "expanded": "e", "index": "106", "rule_match": ["e", "\u204a", "<am>\u204a</am><ex>e</ex>"], "t": "\u204a"}, "Ss": {"original": "\u204a", "fullxml": "<am>\u204a</am><ex>e</ex>", "expanded": "e", "index": "104", "rule_match": ["e", "\u204a", "<am>\u204a</am><ex>e</ex>"], "t": "\u204a"}, "index": "106.1", "S": {"original": "\u204a", "fullxml": "<am>\u204a</am><ex>e</ex>", "expanded": "e", "index": "104", "rule_match": ["e", "\u204a", "<am>\u204a</am><ex>e</ex>"], "t": "\u204a"}, "reading": ["E2", "Ss", "D", "S"]}, {"interface": "entraron", "D": {"original": "entraro\u0304", "fullxml": "entraro<am>\u0304</am><ex>n</ex>", "expanded": "entraron", "index": "108", "rule_match": ["entraron", "entraro\u0304", "entraro<am>\u0304</am><ex>n</ex>"], "t": "entraro\u0304"}, "E2": {"original": "entraron", "index": "108", "rule_match": ["entraron"], "t": "entraron"}, "Ss": {"original": "entraron", "index": "106", "rule_match": ["entraron"], "t": "entraron"}, "index": "108.1", "S": {"original": "entraron", "index": "106", "rule_match": ["entraron"], "t": "entraron"}, "reading": ["E2", "Ss", "D", "S"]}, {"interface": "enlenel", "D": {"original": "enel", "n": "enlenel", "decision_details": [{"scope": "once", "_id": "verse_CPSF:entity=1065:block=2400_164ed26c-a1d5-429e-bc7b-ab2682839a7b", "n": "enlenel", "t": "enel", "class": "none"}], "decision_class": ["none"], "index": "110", "rule_match": ["enel"], "t": "enel"}, "E2": {"original": "enl\u0304enl", "fullxml": "<choice><abbr>enl<am>\u0304</am></abbr><expan>en<ex>e</ex>l</expan></choice>", "expanded": "enlenel", "index": "110", "rule_match": ["enlenel", "enl\u0304enl", "<choice><abbr>enl<am>\u0304</am></abbr><expan>en<ex>e</ex>l</expan></choice>"], "t": "enl\u0304enl"}, "Ss": {"original": "en\u0304l", "n": "enlenel", "fullxml": "en<am>\u0304</am><ex>e</ex>l", "decision_details": [{"scope": "once", "_id": "verse_CPSF:entity=1065:block=2400_456e43aa-a2b5-4f31-94e5-6f34dcf60e41", "n": "enlenel", "t": "enel", "class": "none"}], "expanded": "enel", "decision_class": ["none"], "index": "108", "rule_match": ["enel", "en\u0304l", "en<am>\u0304</am><ex>e</ex>l"], "t": "en\u0304l"}, "index": "110.1", "S": {"original": "enel", "n": "enlenel", "decision_details": [{"scope": "once", "_id": "verse_CPSF:entity=1065:block=2400_19aade32-6306-4b51-85d8-e905494c1bbd", "n": "enlenel", "t": "enel", "class": "none"}], "decision_class": ["none"], "index": "108", "rule_match": ["enel"], "t": "enel"}, "reading": ["E2", "Ss", "D", "S"]}], "suffixes": ["", "", "", ""], "label": "a"}, {"_id": "8606d646021b2d284dda1b28e55c61ac", "standoff_subreadings": ["F"], "details": "lac", "text": [], "created": true, "suffixes": [""], "SR_text": {"F": {"details": "lac verse", "text": [], "type": "lac_verse"}}, "witnesses": ["F"], "type": "lac", "label": "zz"}], "start": 98, "_id": "94de4f790b2f9acc22ce51323ead3a27"}, {"end": 112, "first_word_index": "112.1", "readings": [{"_id": "0b231ded5a4d38355b1b2605eb9d6ec6", "witnesses": ["E2", "S", "Ss"], "text": [{"interface": "castiello", "E2": {"original": "castiello", "index": "112", "rule_match": ["castiello"], "t": "castiello"}, "Ss": {"original": "castiello", "index": "110", "pc_after": ".", "rule_match": ["castiello"], "t": "castiello"}, "index": "112.1", "S": {"original": "castiello", "index": "110", "rule_match": ["castiello"], "t": "castiello"}, "reading": ["Ss", "E2", "S"]}], "suffixes": ["", "", ""], "label": "a"}, {"_id": "c5b68b4fef9b376609872ea3b3efb7cc", "witnesses": ["D"], "text": [{"interface": "castillo", "index": "112.1", "reading": ["D"], "D": {"original": "castillo", "index": "112", "rule_match": ["castillo"], "t": "castillo"}}], "suffixes": [""], "label": "b"}, {"_id": "e7004a97cd3eb9e5d1d27d295200da70", "standoff_subreadings": ["F"], "details": "lac", "text": [], "created": true, "suffixes": [""], "SR_text": {"F": {"details": "lac verse", "text": [], "type": "lac_verse"}}, "witnesses": ["F"], "type": "lac", "label": "zz"}], "start": 112, "_id": "ec13c9c36494d18c8c384cb0a897d98d"}], "lac_readings": ["F"], "om_readings": []}, "algorithm_settings": {"algorithm": "auto", "fuzzy_match": true, "distance": 2}, "TC_context": "CPSF:entity=1065:block=2400", "data_settings": {"base_text": "E2", "base_text_siglum": "E2", "witness_list": ["E2", "D", "F", "S", "Ss"], "language": "undefined"}, "user": "default", "status": "approved"}