{"_id": "CPSF:entity=1074:block=1900_approved_undefined", "context": "D1074S1900", "_model": "collation", "display_settings": {"view_supplied": true, "show_punctuation": false, "show_xml": false, "view_capitalisation": false, "use_lemma": true, "view_unclear": true, "expand_abbreviations": true}, "structure": {"marked_readings": {"regularised": [{"identifier": ["r"], "subreading": [false], "witness": "D", "apparatus": "apparatus", "suffixed_label": [false], "value": "regularised", "suffixed_sigla": [true], "end": 44, "parent_text": "amuy", "start": 44, "reading_history": ["a muy"], "name": ["Regularised"], "reading_text": "a muy", "unit_id": "ae059a3767c0629aad773be704a2b8b1"}, {"identifier": ["r"], "subreading": [false], "witness": "Ss", "apparatus": "apparatus", "suffixed_label": [false], "value": "regularised", "suffixed_sigla": [true], "end": 44, "parent_text": "amuy", "start": 44, "reading_history": ["a muy"], "name": ["Regularised"], "reading_text": "a muy", "unit_id": "ae059a3767c0629aad773be704a2b8b1"}, {"identifier": ["r"], "subreading": [false], "witness": "D", "apparatus": "apparatus", "suffixed_label": [false], "value": "regularised", "suffixed_sigla": [true], "end": 70, "parent_text": "caua&lt;am&gt;\u0142\u0142&lt;/am&gt;&lt;ex&gt;ller&lt;/ex&gt;os", "start": 70, "reading_history": ["caua&lt;am&gt;\u0304&lt;/am&gt;lloscauall&lt;ex&gt;er&lt;/ex&gt;os"], "name": ["Regularised"], "reading_text": "caua&lt;am&gt;\u0304&lt;/am&gt;lloscauall&lt;ex&gt;er&lt;/ex&gt;os", "unit_id": "9813f0fbb7e1fbc7be000d8c3efd6446"}, {"identifier": ["r"], "subreading": [false], "witness": "Ss", "apparatus": "apparatus", "suffixed_label": [false], "value": "regularised", "suffixed_sigla": [true], "end": 70, "parent_text": "caua&lt;am&gt;\u0142\u0142&lt;/am&gt;&lt;ex&gt;ller&lt;/ex&gt;os", "start": 70, "reading_history": ["caualleros"], "name": ["Regularised"], "reading_text": "caualleros", "unit_id": "9813f0fbb7e1fbc7be000d8c3efd6446"}], "none": [{"identifier": [null], "subreading": [false], "witness": "F", "apparatus": "apparatus", "suffixed_label": [false], "value": "none", "suffixed_sigla": [false], "end": 2, "parent_text": "&lt;lac&gt;", "start": 2, "details": "lac verse", "type": "lac_verse", "reading_history": ["&lt;lac verse&gt;"], "name": ["None"], "reading_text": "&lt;lac verse&gt;", "om_details": "lac", "unit_id": "508b92205ca5a6b64eeed86a03516ea6"}, {"identifier": [null], "subreading": [false], "witness": "F", "apparatus": "apparatus", "suffixed_label": [false], "value": "none", "suffixed_sigla": [false], "end": 10, "parent_text": "&lt;lac&gt;", "start": 4, "details": "lac verse", "type": "lac_verse", "reading_history": ["&lt;lac verse&gt;"], "name": ["None"], "reading_text": "&lt;lac verse&gt;", "om_details": "lac", "unit_id": "e3a1d4170b9f40013a5c47329a049c5e"}, {"identifier": [null], "subreading": [false], "witness": "F", "apparatus": "apparatus", "suffixed_label": [false], "value": "none", "suffixed_sigla": [false], "end": 11, "parent_text": "&lt;lac&gt;", "start": 11, "details": "lac verse", "type": "lac_verse", "reading_history": ["&lt;lac verse&gt;"], "name": ["None"], "reading_text": "&lt;lac verse&gt;", "om_details": "lac", "unit_id": "13fe2b437b6536d489c47e9db21b9f6b"}, {"identifier": [null], "subreading": [false], "witness": "F", "apparatus": "apparatus", "suffixed_label": [false], "value": "none", "suffixed_sigla": [false], "end": 12, "parent_text": "&lt;lac&gt;", "start": 12, "details": "lac verse", "type": "lac_verse", "reading_history": ["&lt;lac verse&gt;"], "name": ["None"], "reading_text": "&lt;lac verse&gt;", "om_details": "lac", "unit_id": "7fb72b865236fbe86deeefbb7bf0da63"}, {"identifier": [null], "subreading": [false], "witness": "F", "apparatus": "apparatus", "suffixed_label": [false], "value": "none", "suffixed_sigla": [false], "end": 16, "parent_text": "&lt;lac&gt;", "start": 14, "details": "lac verse", "type": "lac_verse", "reading_history": ["&lt;lac verse&gt;"], "name": ["None"], "reading_text": "&lt;lac verse&gt;", "om_details": "lac", "unit_id": "f2bd1ddadd47509a25df3377ccc38246"}, {"identifier": [null], "subreading": [false], "witness": "F", "apparatus": "apparatus", "suffixed_label": [false], "value": "none", "suffixed_sigla": [false], "end": 18, "parent_text": "&lt;lac&gt;", "start": 18, "details": "lac verse", "type": "lac_verse", "reading_history": ["&lt;lac verse&gt;"], "name": ["None"], "reading_text": "&lt;lac verse&gt;", "om_details": "lac", "unit_id": "14a7cc9950830fb536b4382fdf58490b"}, {"identifier": [null], "subreading": [false], "witness": "F", "apparatus": "apparatus", "suffixed_label": [false], "value": "none", "suffixed_sigla": [false], "end": 22, "parent_text": "&lt;lac&gt;", "start": 20, "details": "lac verse", "type": "lac_verse", "reading_history": ["&lt;lac verse&gt;"], "name": ["None"], "reading_text": "&lt;lac verse&gt;", "om_details": "lac", "unit_id": "770999a9d6466adca63290a1e1ff454e"}, {"identifier": [null], "subreading": [false], "witness": "F", "apparatus": "apparatus", "suffixed_label": [false], "value": "none", "suffixed_sigla": [false], "end": 24, "parent_text": "&lt;lac&gt;", "start": 24, "details": "lac verse", "type": "lac_verse", "reading_history": ["&lt;lac verse&gt;"], "name": ["None"], "reading_text": "&lt;lac verse&gt;", "om_details": "lac", "unit_id": "9627ab1c790937fb745e1b5587bd4150"}, {"identifier": [null], "subreading": [false], "witness": "F", "apparatus": "apparatus", "suffixed_label": [false], "value": "none", "suffixed_sigla": [false], "end": 26, "parent_text": "&lt;lac&gt;", "start": 26, "details": "lac verse", "type": "lac_verse", "reading_history": ["&lt;lac verse&gt;"], "name": ["None"], "reading_text": "&lt;lac verse&gt;", "om_details": "lac", "unit_id": "40c48690e1ca0d91380b3793510537a0"}, {"identifier": [null], "subreading": [false], "witness": "F", "apparatus": "apparatus", "suffixed_label": [false], "value": "none", "suffixed_sigla": [false], "end": 28, "parent_text": "&lt;lac&gt;", "start": 28, "details": "lac verse", "type": "lac_verse", "reading_history": ["&lt;lac verse&gt;"], "name": ["None"], "reading_text": "&lt;lac verse&gt;", "om_details": "lac", "unit_id": "629b4bd787ce4b3ea5656672c41bf1e4"}, {"identifier": [null], "subreading": [false], "witness": "F", "apparatus": "apparatus", "suffixed_label": [false], "value": "none", "suffixed_sigla": [false], "end": 36, "parent_text": "&lt;lac&gt;", "start": 30, "details": "lac verse", "type": "lac_verse", "reading_history": ["&lt;lac verse&gt;"], "name": ["None"], "reading_text": "&lt;lac verse&gt;", "om_details": "lac", "unit_id": "13e72a583e887a2edac78ca08d7fed91"}, {"identifier": [null], "subreading": [false], "witness": "F", "apparatus": "apparatus", "suffixed_label": [false], "value": "none", "suffixed_sigla": [false], "end": 37, "parent_text": "&lt;lac&gt;", "start": 37, "details": "lac verse", "type": "lac_verse", "reading_history": ["&lt;lac verse&gt;"], "name": ["None"], "reading_text": "&lt;lac verse&gt;", "om_details": "lac", "unit_id": "bb900304a5ecfd6d656df5959d926253"}, {"identifier": [null], "subreading": [false], "witness": "F", "apparatus": "apparatus", "suffixed_label": [false], "value": "none", "suffixed_sigla": [false], "end": 40, "parent_text": "&lt;lac&gt;", "start": 38, "details": "lac verse", "type": "lac_verse", "reading_history": ["&lt;lac verse&gt;"], "name": ["None"], "reading_text": "&lt;lac verse&gt;", "om_details": "lac", "unit_id": "f847204103dbc4f04692a010b6239b2f"}, {"identifier": [null], "subreading": [false], "witness": "F", "apparatus": "apparatus", "suffixed_label": [false], "value": "none", "suffixed_sigla": [false], "end": 42, "parent_text": "&lt;lac&gt;", "start": 42, "details": "lac verse", "type": "lac_verse", "reading_history": ["&lt;lac verse&gt;"], "name": ["None"], "reading_text": "&lt;lac verse&gt;", "om_details": "lac", "unit_id": "3c54c94f01dbb1752349e032dcf461b5"}, {"identifier": [null], "subreading": [false], "witness": "F", "apparatus": "apparatus", "suffixed_label": [false], "value": "none", "suffixed_sigla": [false], "end": 44, "parent_text": "&lt;lac&gt;", "start": 44, "details": "lac verse", "type": "lac_verse", "reading_history": ["&lt;lac verse&gt;"], "name": ["None"], "reading_text": "&lt;lac verse&gt;", "om_details": "lac", "unit_id": "ae059a3767c0629aad773be704a2b8b1"}, {"identifier": [null], "subreading": [false], "witness": "F", "apparatus": "apparatus", "suffixed_label": [false], "value": "none", "suffixed_sigla": [false], "end": 46, "parent_text": "&lt;lac&gt;", "start": 46, "details": "lac verse", "type": "lac_verse", "reading_history": ["&lt;lac verse&gt;"], "name": ["None"], "reading_text": "&lt;lac verse&gt;", "om_details": "lac", "unit_id": "8340472169e1d986351b6821973bc9e7"}, {"identifier": [null], "subreading": [false], "witness": "F", "apparatus": "apparatus", "suffixed_label": [false], "value": "none", "suffixed_sigla": [false], "end": 52, "parent_text": "&lt;lac&gt;", "start": 48, "details": "lac verse", "type": "lac_verse", "reading_history": ["&lt;lac verse&gt;"], "name": ["None"], "reading_text": "&lt;lac verse&gt;", "om_details": "lac", "unit_id": "343f503cbbc5d1972cfcc1767feed4d0"}, {"identifier": [null], "subreading": [false], "witness": "F", "apparatus": "apparatus", "suffixed_label": [false], "value": "none", "suffixed_sigla": [false], "end": 54, "parent_text": "&lt;lac&gt;", "start": 54, "details": "lac verse", "type": "lac_verse", "reading_history": ["&lt;lac verse&gt;"], "name": ["None"], "reading_text": "&lt;lac verse&gt;", "om_details": "lac", "unit_id": "06c20dcb6c6149ab4cb8d8da845d393d"}, {"identifier": [null], "subreading": [false], "witness": "F", "apparatus": "apparatus", "suffixed_label": [false], "value": "none", "suffixed_sigla": [false], "end": 66, "parent_text": "&lt;lac&gt;", "start": 56, "details": "lac verse", "type": "lac_verse", "reading_history": ["&lt;lac verse&gt;"], "name": ["None"], "reading_text": "&lt;lac verse&gt;", "om_details": "lac", "unit_id": "5e5a8db21553038b52958be710941f93"}, {"identifier": [null], "subreading": [false], "witness": "F", "apparatus": "apparatus", "suffixed_label": [false], "value": "none", "suffixed_sigla": [false], "end": 68, "parent_text": "&lt;lac&gt;", "start": 68, "details": "lac verse", "type": "lac_verse", "reading_history": ["&lt;lac verse&gt;"], "name": ["None"], "reading_text": "&lt;lac verse&gt;", "om_details": "lac", "unit_id": "1917718ca19f74baadae33446e1f7931"}, {"identifier": [null], "subreading": [false], "witness": "F", "apparatus": "apparatus", "suffixed_label": [false], "value": "none", "suffixed_sigla": [false], "end": 70, "parent_text": "&lt;lac&gt;", "start": 70, "details": "lac verse", "type": "lac_verse", "reading_history": ["&lt;lac verse&gt;"], "name": ["None"], "reading_text": "&lt;lac verse&gt;", "om_details": "lac", "unit_id": "9813f0fbb7e1fbc7be000d8c3efd6446"}]}, "hand_id_map": {"Ss": "Ss", "F": "F", "E2": "E2", "S": "S", "D": "D"}, "overtext_name": "E2", "overtext": [{"tokens": [{"original": "\u204a", "pc_before": "\u00b6&nbsp;", "expanded": "e", "index": "2", "rule_match": ["e", "\u204a", "<am>\u204a</am><ex>e</ex>"], "reading": "E2", "fullxml": "<am>\u204a</am><ex>e</ex>", "t": "\u204a"}, {"original": "q\u1d45ndo", "fullxml": "q<am>\u1d45</am><ex>ua</ex>ndo", "expanded": "quando", "index": "4", "rule_match": ["quando", "q\u1d45ndo", "q<am>\u1d45</am><ex>ua</ex>ndo"], "reading": "E2", "t": "q\u1d45ndo"}, {"original": "el", "index": "6", "rule_match": ["el"], "reading": "E2", "t": "el"}, {"original": "Rey", "index": "8", "rule_match": ["Rey", "rey"], "reading": "E2", "t": "Rey"}, {"original": "don", "index": "10", "rule_match": ["don"], "reading": "E2", "t": "don"}, {"original": "fernando", "index": "12", "rule_match": ["fernando"], "reading": "E2", "t": "fernando"}, {"original": "agranada", "index": "14", "rule_match": ["agranada"], "reading": "E2", "t": "agranada"}, {"original": "llego", "index": "16", "rule_match": ["llego"], "reading": "E2", "t": "llego"}, {"original": "auie", "index": "18", "rule_match": ["auie"], "reading": "E2", "t": "auie"}, {"original": "ya", "index": "20", "rule_match": ["ya"], "reading": "E2", "t": "ya"}, {"original": "bien", "index": "22", "rule_match": ["bien"], "reading": "E2", "t": "bien"}, {"original": "diez", "index": "24", "rule_match": ["diez"], "reading": "E2", "t": "diez"}, {"original": "dias", "index": "26", "rule_match": ["dias"], "reading": "E2", "t": "dias"}, {"original": "que", "index": "28", "rule_match": ["que"], "reading": "E2", "t": "que"}, {"original": "era", "index": "30", "rule_match": ["era"], "reading": "E2", "t": "era"}, {"original": "y", "index": "32", "rule_match": ["y"], "reading": "E2", "t": "y"}, {"original": "su", "index": "34", "rule_match": ["su"], "reading": "E2", "t": "su"}, {"original": "\u0127mano", "fullxml": "<unclear><am>\u0127</am><ex>her</ex></unclear>mano", "expanded": "hermano", "index": "36", "rule_match": ["hermano", "\u0127mano", "<unclear><am>\u0127</am><ex>her</ex></unclear>mano"], "reading": "E2", "t": "\u0127mano"}, {"original": "q\u0304", "fullxml": "q<am>\u0304</am><ex>ue</ex>", "expanded": "que", "index": "38", "rule_match": ["que", "q\u0304", "q<am>\u0304</am><ex>ue</ex>"], "reading": "E2", "t": "q\u0304"}, {"original": "estaua", "index": "40", "rule_match": ["estaua"], "reading": "E2", "t": "estaua"}, {"original": "y", "index": "42", "rule_match": ["y"], "reading": "E2", "t": "y"}, {"original": "amuy", "index": "44", "rule_match": ["amuy"], "reading": "E2", "t": "amuy"}, {"original": "grant", "index": "46", "rule_match": ["grant"], "reading": "E2", "t": "grant"}, {"original": "peligro", "index": "48", "rule_match": ["peligro"], "reading": "E2", "t": "peligro"}, {"original": "\u204a", "fullxml": "<am>\u204a</am><ex>e</ex>", "expanded": "e", "index": "50", "rule_match": ["e", "\u204a", "<am>\u204a</am><ex>e</ex>"], "reading": "E2", "t": "\u204a"}, {"original": "yazie", "index": "52", "rule_match": ["yazie"], "reading": "E2", "t": "yazie"}, {"original": "y", "index": "54", "rule_match": ["y"], "reading": "E2", "t": "y"}, {"original": "dentro", "index": "56", "rule_match": ["dentro"], "reading": "E2", "t": "dentro"}, {"original": "el", "index": "58", "rule_match": ["el"], "reading": "E2", "t": "el"}, {"original": "Rey", "index": "60", "rule_match": ["Rey", "rey"], "reading": "E2", "t": "Rey"}, {"original": "de", "index": "62", "rule_match": ["de"], "reading": "E2", "t": "de"}, {"original": "granada", "index": "64", "rule_match": ["granada"], "reading": "E2", "t": "granada"}, {"original": "con", "index": "66", "rule_match": ["con"], "reading": "E2", "t": "con"}, {"original": "ocho\u00e7ie\u0304tos", "fullxml": "ocho\u00e7ie<am>\u0304</am><ex>n</ex>tos", "expanded": "ocho\u00e7ientos", "index": "68", "rule_match": ["ocho\u00e7ientos", "ocho\u00e7ie\u0304tos", "ocho\u00e7ie<am>\u0304</am><ex>n</ex>tos"], "reading": "E2", "t": "ocho\u00e7ie\u0304tos"}, {"original": "ocho\u00e7ie\u0304tos", "fullxml": "caua<am>\u0142\u0142</am><ex>ller</ex>os", "expanded": "caua<am>\u0142\u0142</am><ex>ller</ex>os", "index": "70", "rule_match": ["caua<am>\u0142\u0142</am><ex>ller</ex>os", "ocho\u00e7ie\u0304tos", "caua<am>\u0142\u0142</am><ex>ller</ex>os"], "reading": "E2", "t": "ocho\u00e7ie\u0304tos"}], "id": "E2"}], "apparatus": [{"end": 2, "first_word_index": "2.1", "readings": [{"_id": "d009df8a90ab2a4d2cb185d038a6b75e", "witnesses": ["D", "E2", "S", "Ss"], "text": [{"interface": "e", "D": {"original": "E", "index": "2", "rule_match": ["E", "e"], "pc_before": "\u00b6&nbsp;", "t": "E"}, "E2": {"original": "\u204a", "pc_before": "\u00b6&nbsp;", "expanded": "e", "index": "2", "rule_match": ["e", "\u204a", "<am>\u204a</am><ex>e</ex>"], "fullxml": "<am>\u204a</am><ex>e</ex>", "t": "\u204a"}, "Ss": {"original": "E", "index": "2", "rule_match": ["E", "e"], "t": "E"}, "index": "2.1", "S": {"original": "\u204a", "fullxml": "<am>\u204a</am><ex>e</ex>", "expanded": "e", "index": "2", "rule_match": ["e", "\u204a", "<am>\u204a</am><ex>e</ex>"], "t": "\u204a"}, "reading": ["D", "E2", "S", "Ss"]}], "suffixes": ["", "", "", ""], "label": "a"}, {"_id": "bfdda6ad8ea1a365d780e780601d9a39", "standoff_subreadings": ["F"], "details": "lac", "text": [], "created": true, "suffixes": [""], "SR_text": {"F": {"details": "lac verse", "text": [], "type": "lac_verse"}}, "witnesses": ["F"], "type": "lac", "label": "zz"}], "start": 2, "_id": "508b92205ca5a6b64eeed86a03516ea6"}, {"end": 10, "first_word_index": "4.1", "readings": [{"_id": "2d737bc3b088ab431b13d8b5fc128df2", "witnesses": ["D", "E2", "S", "Ss"], "text": [{"interface": "quando", "D": {"original": "qua\u0304do", "fullxml": "qua<am>\u0304</am><ex>n</ex>do", "expanded": "quando", "index": "4", "rule_match": ["quando", "qua\u0304do", "qua<am>\u0304</am><ex>n</ex>do"], "t": "qua\u0304do"}, "E2": {"original": "q\u1d45ndo", "fullxml": "q<am>\u1d45</am><ex>ua</ex>ndo", "expanded": "quando", "index": "4", "rule_match": ["quando", "q\u1d45ndo", "q<am>\u1d45</am><ex>ua</ex>ndo"], "t": "q\u1d45ndo"}, "Ss": {"original": "qua\u0304do", "fullxml": "qua<am>\u0304</am><ex>n</ex>do", "expanded": "quando", "index": "4", "rule_match": ["quando", "qua\u0304do", "qua<am>\u0304</am><ex>n</ex>do"], "t": "qua\u0304do"}, "index": "4.1", "S": {"original": "q\u0304ndo", "fullxml": "q<am>\u0304</am><ex>ua</ex>ndo", "expanded": "quando", "index": "4", "rule_match": ["quando", "q\u0304ndo", "q<am>\u0304</am><ex>ua</ex>ndo"], "t": "q\u0304ndo"}, "reading": ["D", "E2", "S", "Ss"]}, {"interface": "el", "D": {"original": "el", "index": "6", "rule_match": ["el"], "t": "el"}, "E2": {"original": "el", "index": "6", "rule_match": ["el"], "t": "el"}, "Ss": {"original": "el", "index": "6", "rule_match": ["el"], "t": "el"}, "index": "6", "S": {"original": "el", "index": "6", "rule_match": ["el"], "t": "el"}, "reading": ["D", "E2", "S", "Ss"]}, {"interface": "rey", "D": {"original": "Rey", "index": "8", "rule_match": ["Rey", "rey"], "t": "Rey"}, "E2": {"original": "Rey", "index": "8", "rule_match": ["Rey", "rey"], "t": "Rey"}, "Ss": {"original": "Rey", "n": "rey", "fullxml": "<choice><abbr><am><g>R</g></am></abbr><expan><ex>rr</ex></expan></choice>ey", "decision_details": [{"scope": "once", "_id": "verse_CPSF:entity=1074:block=1900_7f2d0470-1e39-4d04-8002-f84e576813de", "n": "rey", "t": "rrey", "class": "none"}], "expanded": "rrey", "decision_class": ["none"], "index": "8", "rule_match": ["rrey", "Rey", "<choice><abbr><am><g>R</g></am></abbr><expan><ex>rr</ex></expan></choice>ey", "<choice><abbr><am><g>r</g></am></abbr><expan><ex>rr</ex></expan></choice>ey"], "t": "Rey"}, "index": "8", "S": {"original": "rrey", "fullxml": "<choice><abbr><am><g>rr</g></am></abbr><expan><ex>R</ex></expan></choice>ey", "expanded": "Rey", "index": "8", "rule_match": ["Rey", "rrey", "<choice><abbr><am><g>rr</g></am></abbr><expan><ex>R</ex></expan></choice>ey", "rey", "<choice><abbr><am><g>rr</g></am></abbr><expan><ex>r</ex></expan></choice>ey"], "t": "rrey"}, "reading": ["D", "E2", "S", "Ss"]}, {"interface": "don", "D": {"original": "don", "index": "10", "rule_match": ["don"], "t": "don"}, "E2": {"original": "don", "index": "10", "rule_match": ["don"], "t": "don"}, "Ss": {"original": "don", "index": "10", "rule_match": ["don"], "t": "don"}, "index": "10", "S": {"original": "don", "index": "10", "rule_match": ["don"], "t": "don"}, "reading": ["D", "E2", "S", "Ss"]}], "suffixes": ["", "", "", ""], "label": "a"}, {"_id": "db6703ca106089d16fd73f86332bad89", "standoff_subreadings": ["F"], "details": "lac", "text": [], "created": true, "suffixes": [""], "SR_text": {"F": {"details": "lac verse", "text": [], "type": "lac_verse"}}, "witnesses": ["F"], "type": "lac", "label": "zz"}], "start": 4, "_id": "e3a1d4170b9f40013a5c47329a049c5e"}, {"end": 11, "first_word_index": "11.1", "readings": [{"_id": "a2d6b29e27f4b71ab99dfaac370f91b1", "suffixes": ["", "", ""], "text": [], "witnesses": ["E2", "S", "Ss"], "type": "om", "label": "a"}, {"_id": "ce930ffd541f840287762376e6b18dad", "witnesses": ["D"], "text": [{"interface": "alfonso", "index": "11.1", "reading": ["D"], "D": {"original": "alfon\u0304", "fullxml": "<seg&nbsp;rend=''strike''>alfon<am>\u0304</am><ex>so</ex></seg>", "expanded": "alfonso", "index": "12", "rule_match": ["alfonso", "alfon\u0304", "<seg rend=''strike''>alfon<am>\u0304</am><ex>so</ex></seg>"], "t": "alfon\u0304"}}], "suffixes": [""], "label": "b"}, {"_id": "03330bb616c4564db8de50c98cfdaf3f", "standoff_subreadings": ["F"], "details": "lac", "text": [], "created": true, "suffixes": [""], "SR_text": {"F": {"details": "lac verse", "text": [], "type": "lac_verse"}}, "witnesses": ["F"], "type": "lac", "label": "zz"}], "start": 11, "_id": "13fe2b437b6536d489c47e9db21b9f6b"}, {"end": 12, "first_word_index": "12.1", "readings": [{"_id": "f4bac3a1d75dbc247dae3114448311e6", "witnesses": ["E2"], "text": [{"interface": "fernando", "index": "12.1", "E2": {"original": "fernando", "index": "12", "rule_match": ["fernando"], "t": "fernando"}, "reading": ["E2"]}], "suffixes": [""], "label": "a"}, {"_id": "296dfd83f423468d894f5a88a8bbf9f6", "witnesses": ["Ss"], "text": [{"Ss": {"original": "ferrando", "index": "12", "rule_match": ["ferrando"], "t": "ferrando"}, "index": "12.1", "interface": "ferrando", "reading": ["Ss"]}], "suffixes": [""], "label": "b"}, {"_id": "bebef6999de99c0818f2a074bae110d0", "witnesses": ["D", "S"], "text": [{"interface": "ferrnando", "index": "12.1", "S": {"original": "ferrnando", "index": "12", "rule_match": ["ferrnando"], "t": "ferrnando"}, "reading": ["D", "S"], "D": {"original": "ferrna\u0304do", "fullxml": "ferrna<am>\u0304</am><ex>n</ex>do", "expanded": "ferrnando", "index": "14", "rule_match": ["ferrnando", "ferrna\u0304do", "ferrna<am>\u0304</am><ex>n</ex>do"], "t": "ferrna\u0304do"}}], "suffixes": ["", ""], "label": "c"}, {"_id": "415f4f691dcea89764840147a8843a4f", "standoff_subreadings": ["F"], "details": "lac", "text": [], "created": true, "suffixes": [""], "SR_text": {"F": {"details": "lac verse", "text": [], "type": "lac_verse"}}, "witnesses": ["F"], "type": "lac", "label": "zz"}], "start": 12, "_id": "7fb72b865236fbe86deeefbb7bf0da63"}, {"end": 16, "first_word_index": "14.1", "readings": [{"_id": "4a8e8d3894c6317e524fd74ee4c9d051", "witnesses": ["D", "E2", "S", "Ss"], "text": [{"interface": "agranada", "D": {"original": "agranada", "index": "16", "rule_match": ["agranada"], "t": "agranada"}, "E2": {"original": "agranada", "index": "14", "rule_match": ["agranada"], "t": "agranada"}, "Ss": {"original": "agranada", "index": "14", "rule_match": ["agranada"], "t": "agranada"}, "index": "14.1", "S": {"original": "agranada", "index": "14", "rule_match": ["agranada"], "t": "agranada"}, "reading": ["E2", "S", "D", "Ss"]}, {"interface": "llego", "D": {"original": "llego", "index": "18", "rule_match": ["llego"], "t": "llego"}, "E2": {"original": "llego", "index": "16", "rule_match": ["llego"], "t": "llego"}, "Ss": {"original": "llego", "index": "16", "rule_match": ["llego"], "t": "llego"}, "index": "16.1", "S": {"original": "llego", "index": "16", "rule_match": ["llego"], "t": "llego"}, "reading": ["E2", "S", "D", "Ss"]}], "suffixes": ["", "", "", ""], "label": "a"}, {"_id": "43608e274438e0e9952b73ed5c7c3d87", "standoff_subreadings": ["F"], "details": "lac", "text": [], "created": true, "suffixes": [""], "SR_text": {"F": {"details": "lac verse", "text": [], "type": "lac_verse"}}, "witnesses": ["F"], "type": "lac", "label": "zz"}], "start": 14, "_id": "f2bd1ddadd47509a25df3377ccc38246"}, {"end": 18, "first_word_index": "18.1", "readings": [{"_id": "9b9f7da5b717a0ecdbe3f5c0f0fa4cc3", "witnesses": ["E2"], "text": [{"interface": "auie", "index": "18.1", "E2": {"original": "auie", "index": "18", "rule_match": ["auie"], "t": "auie"}, "reading": ["E2"]}], "suffixes": [""], "label": "a"}, {"_id": "2588d82cb263fbf74f9c5a3a3acdd395", "witnesses": ["D", "S", "Ss"], "text": [{"interface": "auja", "D": {"original": "auja", "index": "20", "rule_match": ["auja"], "t": "auja"}, "Ss": {"original": "avia", "n": "auja", "decision_details": [{"scope": "once", "_id": "verse_CPSF:entity=1074:block=1900_b802ff96-9a91-49f1-bcfa-ddbbf9d81108", "n": "auja", "t": "avia", "class": "none"}], "decision_class": ["none"], "index": "18", "rule_match": ["avia"], "t": "avia"}, "index": "18.1", "S": {"original": "auja", "index": "18", "rule_match": ["auja"], "t": "auja"}, "reading": ["D", "S", "Ss"]}], "suffixes": ["", "", ""], "label": "b"}, {"_id": "45a95d6f2bfb26fac04867df92a25047", "standoff_subreadings": ["F"], "details": "lac", "text": [], "created": true, "suffixes": [""], "SR_text": {"F": {"details": "lac verse", "text": [], "type": "lac_verse"}}, "witnesses": ["F"], "type": "lac", "label": "zz"}], "start": 18, "_id": "14a7cc9950830fb536b4382fdf58490b"}, {"end": 22, "first_word_index": "20.1", "readings": [{"_id": "6d26120287d571b6d789b8c1088985a0", "witnesses": ["D", "E2", "S", "Ss"], "text": [{"interface": "ya", "D": {"original": "ya", "index": "22", "rule_match": ["ya"], "t": "ya"}, "E2": {"original": "ya", "index": "20", "rule_match": ["ya"], "t": "ya"}, "Ss": {"original": "ya", "index": "20", "rule_match": ["ya"], "t": "ya"}, "index": "20.1", "S": {"original": "ya", "index": "20", "rule_match": ["ya"], "t": "ya"}, "reading": ["E2", "S", "D", "Ss"]}, {"interface": "bien", "D": {"original": "bie\u0304", "fullxml": "bie<am>\u0304</am><ex>n</ex>", "expanded": "bien", "index": "24", "rule_match": ["bien", "bie\u0304", "bie<am>\u0304</am><ex>n</ex>"], "t": "bie\u0304"}, "E2": {"original": "bien", "index": "22", "rule_match": ["bien"], "t": "bien"}, "Ss": {"original": "bien", "index": "22", "rule_match": ["bien"], "t": "bien"}, "index": "22.1", "S": {"original": "bien", "index": "22", "rule_match": ["bien"], "t": "bien"}, "reading": ["E2", "S", "D", "Ss"]}], "suffixes": ["", "", "", ""], "label": "a"}, {"_id": "10378c03c026390974531ccb4e9bcfdf", "standoff_subreadings": ["F"], "details": "lac", "text": [], "created": true, "suffixes": [""], "SR_text": {"F": {"details": "lac verse", "text": [], "type": "lac_verse"}}, "witnesses": ["F"], "type": "lac", "label": "zz"}], "start": 20, "_id": "770999a9d6466adca63290a1e1ff454e"}, {"end": 24, "first_word_index": "24.1", "readings": [{"_id": "cc7c1ebe4d3d55dea0ce1918474163a4", "witnesses": ["D", "E2", "S"], "text": [{"interface": "diez", "D": {"original": "diez", "index": "26", "rule_match": ["diez"], "t": "diez"}, "E2": {"original": "diez", "index": "24", "rule_match": ["diez"], "t": "diez"}, "index": "24.1", "S": {"original": "diez", "index": "24", "rule_match": ["diez"], "t": "diez"}, "reading": ["E2", "D", "S"]}], "suffixes": ["", "", ""], "label": "a"}, {"_id": "12db96e5c70acc09ae946833ab7edc52", "witnesses": ["Ss"], "text": [{"Ss": {"original": "dies", "index": "24", "rule_match": ["dies"], "t": "dies"}, "index": "24.1", "interface": "dies", "reading": ["Ss"]}], "suffixes": [""], "label": "b"}, {"_id": "d374f9511cbea63c4690609bb5427e8b", "standoff_subreadings": ["F"], "details": "lac", "text": [], "created": true, "suffixes": [""], "SR_text": {"F": {"details": "lac verse", "text": [], "type": "lac_verse"}}, "witnesses": ["F"], "type": "lac", "label": "zz"}], "start": 24, "_id": "9627ab1c790937fb745e1b5587bd4150"}, {"end": 26, "first_word_index": "26.1", "readings": [{"_id": "4a75912a9ebea2ba94b79709e6377407", "witnesses": ["D", "E2", "S", "Ss"], "text": [{"interface": "dias", "D": {"original": "dias", "index": "28", "rule_match": ["dias"], "t": "dias"}, "E2": {"original": "dias", "index": "26", "rule_match": ["dias"], "t": "dias"}, "Ss": {"original": "dias", "index": "26", "rule_match": ["dias"], "t": "dias"}, "index": "26.1", "S": {"original": "dias", "index": "26", "rule_match": ["dias"], "t": "dias"}, "reading": ["E2", "D", "S", "Ss"]}], "suffixes": ["", "", "", ""], "label": "a"}, {"_id": "433c9b06e64bc722b1c07cf83022557d", "standoff_subreadings": ["F"], "details": "lac", "text": [], "created": true, "suffixes": [""], "SR_text": {"F": {"details": "lac verse", "text": [], "type": "lac_verse"}}, "witnesses": ["F"], "type": "lac", "label": "zz"}], "start": 26, "_id": "40c48690e1ca0d91380b3793510537a0"}, {"end": 28, "first_word_index": "28.1", "readings": [{"_id": "4a87b498811c53c26d8da19bef31940f", "witnesses": ["D", "E2", "S", "Ss"], "text": [{"interface": "que", "D": {"original": "que", "index": "30", "rule_match": ["que"], "t": "que"}, "E2": {"original": "que", "index": "28", "rule_match": ["que"], "t": "que"}, "Ss": {"original": "que", "index": "28", "rule_match": ["que"], "t": "que"}, "index": "28.1", "S": {"original": "que", "index": "28", "rule_match": ["que"], "t": "que"}, "reading": ["D", "E2", "S", "Ss"]}], "suffixes": ["", "", "", ""], "label": "a"}, {"_id": "0e6a0244e0b6873daca481cc7d32ca0c", "standoff_subreadings": ["F"], "details": "lac", "text": [], "created": true, "suffixes": [""], "SR_text": {"F": {"details": "lac verse", "text": [], "type": "lac_verse"}}, "witnesses": ["F"], "type": "lac", "label": "zz"}], "start": 28, "_id": "629b4bd787ce4b3ea5656672c41bf1e4"}, {"end": 36, "first_word_index": "30.1", "readings": [{"_id": "e1498d60171e7fbd0aca3d7d69a1484a", "witnesses": ["D", "E2", "S"], "text": [{"interface": "era", "D": {"original": "era", "index": "32", "rule_match": ["era"], "t": "era"}, "E2": {"original": "era", "index": "30", "rule_match": ["era"], "t": "era"}, "index": "30.1", "S": {"original": "era", "index": "30", "rule_match": ["era"], "t": "era"}, "reading": ["D", "E2", "S"]}, {"interface": "y", "D": {"original": "y", "index": "34", "rule_match": ["y"], "t": "y"}, "E2": {"original": "y", "index": "32", "rule_match": ["y"], "t": "y"}, "index": "32.1", "S": {"original": "y", "index": "32", "rule_match": ["y"], "t": "y"}, "reading": ["D", "E2", "S"]}, {"interface": "su", "D": {"original": "su", "index": "36", "rule_match": ["su"], "t": "su"}, "E2": {"original": "su", "index": "34", "rule_match": ["su"], "t": "su"}, "index": "34.1", "S": {"original": "su", "index": "34", "rule_match": ["su"], "t": "su"}, "reading": ["D", "E2", "S"]}, {"interface": "hermano", "D": {"original": "he\u0309mano", "fullxml": "he<am>\u0309</am><ex>r</ex>mano", "expanded": "hermano", "index": "38", "rule_match": ["hermano", "he\u0309mano", "he<am>\u0309</am><ex>r</ex>mano"], "t": "he\u0309mano"}, "E2": {"original": "\u0127mano", "fullxml": "<unclear><am>\u0127</am><ex>her</ex></unclear>mano", "expanded": "hermano", "index": "36", "rule_match": ["hermano", "\u0127mano", "<unclear><am>\u0127</am><ex>her</ex></unclear>mano"], "t": "\u0127mano"}, "index": "36.1", "S": {"original": "hermano", "index": "36", "rule_match": ["hermano"], "t": "hermano"}, "reading": ["D", "E2", "S"]}], "suffixes": ["", "", ""], "label": "a"}, {"_id": "643afe0a9650a78e4185fa35a812b56c", "witnesses": ["Ss"], "text": [{"interface": "su", "index": "30.1", "reading": ["Ss"], "Ss": {"original": "su", "index": "30", "rule_match": ["su"], "t": "su"}}, {"interface": "hermano", "index": "30.2", "reading": ["Ss"], "Ss": {"original": "hermano", "index": "32", "rule_match": ["hermano"], "t": "hermano"}}, {"interface": "era", "index": "30.3", "reading": ["Ss"], "Ss": {"original": "era", "index": "34", "rule_match": ["era"], "t": "era"}}, {"interface": "y", "index": "32.1", "reading": ["Ss"], "Ss": {"original": "y", "index": "36", "rule_match": ["y"], "t": "y"}}], "suffixes": [""], "label": "b"}, {"_id": "95e991efbdb579704ec65bc43fc6e2f0", "standoff_subreadings": ["F"], "details": "lac", "text": [], "created": true, "suffixes": [""], "SR_text": {"F": {"details": "lac verse", "text": [], "type": "lac_verse"}}, "witnesses": ["F"], "type": "lac", "label": "zz"}], "start": 30, "_id": "13e72a583e887a2edac78ca08d7fed91"}, {"end": 37, "first_word_index": "37.1", "readings": [{"_id": "b8a1184e5e5e9b299ec52806569a22bc", "suffixes": ["", ""], "text": [], "witnesses": ["E2", "S"], "type": "om", "label": "a"}, {"_id": "cc9a0f170e0023cc86913c4c9582bc0e", "witnesses": ["D", "Ss"], "text": [{"Ss": {"original": "\u204a", "fullxml": "<am>\u204a</am><ex>e</ex>", "expanded": "e", "index": "38", "rule_match": ["e", "\u204a", "<am>\u204a</am><ex>e</ex>"], "t": "\u204a"}, "index": "37.1", "interface": "e", "reading": ["D", "Ss"], "D": {"original": "\u204a", "fullxml": "<am>\u204a</am><ex>e</ex>", "expanded": "e", "index": "40", "rule_match": ["e", "\u204a", "<am>\u204a</am><ex>e</ex>"], "t": "\u204a"}}], "suffixes": ["", ""], "label": "b"}, {"_id": "315c5e4fe99645558333c3f8e3962b25", "standoff_subreadings": ["F"], "details": "lac", "text": [], "created": true, "suffixes": [""], "SR_text": {"F": {"details": "lac verse", "text": [], "type": "lac_verse"}}, "witnesses": ["F"], "type": "lac", "label": "zz"}], "start": 37, "_id": "bb900304a5ecfd6d656df5959d926253"}, {"end": 40, "first_word_index": "38", "readings": [{"_id": "c0e0e0b2f944da79a3191b0fc5297498", "witnesses": ["D", "E2", "S", "Ss"], "text": [{"interface": "que", "D": {"original": "q\u0304", "fullxml": "q<am>\u0304</am><ex>ue</ex>", "expanded": "que", "index": "42", "rule_match": ["que", "q\u0304", "q<am>\u0304</am><ex>ue</ex>"], "t": "q\u0304"}, "E2": {"original": "q\u0304", "fullxml": "q<am>\u0304</am><ex>ue</ex>", "expanded": "que", "index": "38", "rule_match": ["que", "q\u0304", "q<am>\u0304</am><ex>ue</ex>"], "t": "q\u0304"}, "Ss": {"original": "que", "index": "40", "rule_match": ["que"], "t": "que"}, "index": "38", "S": {"original": "que", "index": "38", "rule_match": ["que"], "t": "que"}, "reading": ["D", "E2", "S", "Ss"]}, {"interface": "estaua", "D": {"original": "estaua", "index": "44", "rule_match": ["estaua"], "t": "estaua"}, "E2": {"original": "estaua", "index": "40", "rule_match": ["estaua"], "t": "estaua"}, "Ss": {"original": "estaua", "index": "42", "rule_match": ["estaua"], "t": "estaua"}, "index": "40", "S": {"original": "estaua", "index": "40", "rule_match": ["estaua"], "t": "estaua"}, "reading": ["D", "E2", "S", "Ss"]}], "suffixes": ["", "", "", ""], "label": "a"}, {"_id": "9eace5b3e110c7b250b6b2947a79be74", "standoff_subreadings": ["F"], "details": "lac", "text": [], "created": true, "suffixes": [""], "SR_text": {"F": {"details": "lac verse", "text": [], "type": "lac_verse"}}, "witnesses": ["F"], "type": "lac", "label": "zz"}], "start": 38, "_id": "f847204103dbc4f04692a010b6239b2f"}, {"end": 42, "first_word_index": "42.1", "readings": [{"_id": "0aa5b2fb7905babd49a59b98797f3036", "witnesses": ["E2", "S"], "text": [{"interface": "y", "index": "42.1", "E2": {"original": "y", "index": "42", "rule_match": ["y"], "t": "y"}, "S": {"original": "y", "index": "42", "rule_match": ["y"], "t": "y"}, "reading": ["E2", "S"]}], "suffixes": ["", ""], "label": "a"}, {"_id": "585de56906d86bd7c74ae55c768cd9ff", "witnesses": ["D", "Ss"], "text": [{"interface": "ay", "index": "42.1", "reading": ["D", "Ss"], "Ss": {"original": "ay", "index": "44", "rule_match": ["ay"], "t": "ay"}, "D": {"original": "ay", "index": "46", "rule_match": ["ay"], "t": "ay"}}], "suffixes": ["", ""], "label": "b"}, {"_id": "ca68b65c761560edff5ed5b1e996156f", "standoff_subreadings": ["F"], "details": "lac", "text": [], "created": true, "suffixes": [""], "SR_text": {"F": {"details": "lac verse", "text": [], "type": "lac_verse"}}, "witnesses": ["F"], "type": "lac", "label": "zz"}], "start": 42, "_id": "3c54c94f01dbb1752349e032dcf461b5"}, {"end": 44, "first_word_index": "44.1", "readings": [{"_id": "d7d15a5afadfe9ff360ce9120cfd40a0", "standoff_subreadings": ["D", "Ss"], "text": [{"interface": "amuy", "index": "44.1", "E2": {"original": "amuy", "index": "44", "rule_match": ["amuy"], "t": "amuy"}, "S": {"original": "amuy", "index": "44", "rule_match": ["amuy"], "t": "amuy"}, "reading": ["E2", "S"]}], "SR_text": {"Ss": {"text": [{"interface": "a", "index": "44.1", "reading": ["Ss"], "Ss": {"original": "a", "index": "46", "rule_match": ["a"], "interface": "a", "t": "a"}}, {"interface": "muy", "index": "44.2", "reading": ["Ss"], "Ss": {"original": "muy", "index": "48", "rule_match": ["muy"], "interface": "muy", "t": "muy"}}]}, "D": {"text": [{"interface": "a", "index": "44.1", "reading": ["D"], "D": {"original": "a", "index": "48", "rule_match": ["a"], "interface": "a", "t": "a"}}, {"interface": "muy", "index": "44.2", "reading": ["D"], "D": {"original": "muy", "index": "50", "rule_match": ["muy"], "interface": "muy", "t": "muy"}}]}}, "witnesses": ["D", "E2", "S", "Ss"], "suffixes": ["r", "", "", "r"], "label": "a"}, {"_id": "c9a588185f672a9f484d060d76bdbb65", "standoff_subreadings": ["F"], "details": "lac", "text": [], "created": true, "suffixes": [""], "SR_text": {"F": {"details": "lac verse", "text": [], "type": "lac_verse"}}, "witnesses": ["F"], "type": "lac", "label": "zz"}], "start": 44, "_id": "ae059a3767c0629aad773be704a2b8b1"}, {"end": 46, "first_word_index": "46.1", "readings": [{"_id": "9d17857222a248d815ecea2e87e956c8", "witnesses": ["E2", "Ss"], "text": [{"Ss": {"original": "grant", "index": "50", "rule_match": ["grant"], "t": "grant"}, "index": "46.1", "E2": {"original": "grant", "index": "46", "rule_match": ["grant"], "t": "grant"}, "interface": "grant", "reading": ["E2", "Ss"]}], "suffixes": ["", ""], "label": "a"}, {"_id": "714c2f675a92451759a6c8b394b464f0", "witnesses": ["S"], "text": [{"interface": "grand", "index": "46.1", "S": {"original": "grand", "index": "46", "rule_match": ["grand"], "t": "grand"}, "reading": ["S"]}], "suffixes": [""], "label": "b"}, {"_id": "1fc086270e0fb2014948719086dbf706", "witnesses": ["D"], "text": [{"interface": "grande", "index": "46.1", "reading": ["D"], "D": {"original": "grande", "index": "52", "rule_match": ["grande"], "t": "grande"}}], "suffixes": [""], "label": "c"}, {"_id": "f38bce1d56924bbaf382d7c491c984ee", "standoff_subreadings": ["F"], "details": "lac", "text": [], "created": true, "suffixes": [""], "SR_text": {"F": {"details": "lac verse", "text": [], "type": "lac_verse"}}, "witnesses": ["F"], "type": "lac", "label": "zz"}], "start": 46, "_id": "8340472169e1d986351b6821973bc9e7"}, {"end": 52, "first_word_index": "48.1", "readings": [{"_id": "540db328118e0a1eb192612b912c1866", "witnesses": ["D", "E2", "S", "Ss"], "text": [{"interface": "peligro", "D": {"original": "peligro", "index": "54", "pc_after": "&nbsp;\u00b6 ", "rule_match": ["peligro"], "t": "peligro"}, "E2": {"original": "peligro", "index": "48", "rule_match": ["peligro"], "t": "peligro"}, "Ss": {"original": "peligro", "index": "52", "rule_match": ["peligro"], "t": "peligro"}, "index": "48.1", "S": {"original": "peligro", "index": "48", "rule_match": ["peligro"], "t": "peligro"}, "reading": ["D", "E2", "Ss", "S"]}, {"interface": "e", "D": {"original": "E", "index": "56", "rule_match": ["E", "e"], "t": "E"}, "E2": {"original": "\u204a", "fullxml": "<am>\u204a</am><ex>e</ex>", "expanded": "e", "index": "50", "rule_match": ["e", "\u204a", "<am>\u204a</am><ex>e</ex>"], "t": "\u204a"}, "Ss": {"original": "\u204a", "fullxml": "<am>\u204a</am><ex>e</ex>", "expanded": "e", "index": "54", "rule_match": ["e", "\u204a", "<am>\u204a</am><ex>e</ex>"], "t": "\u204a"}, "index": "50.1", "S": {"original": "\u204a", "fullxml": "<am>\u204a</am><ex>e</ex>", "expanded": "e", "index": "50", "rule_match": ["e", "\u204a", "<am>\u204a</am><ex>e</ex>"], "t": "\u204a"}, "reading": ["D", "E2", "Ss", "S"]}, {"interface": "yazie", "D": {"original": "yazie", "index": "58", "rule_match": ["yazie"], "t": "yazie"}, "E2": {"original": "yazie", "index": "52", "rule_match": ["yazie"], "t": "yazie"}, "Ss": {"original": "yazie", "index": "56", "rule_match": ["yazie"], "t": "yazie"}, "index": "52.1", "S": {"original": "yazie", "index": "52", "rule_match": ["yazie"], "t": "yazie"}, "reading": ["D", "E2", "Ss", "S"]}], "suffixes": ["", "", "", ""], "label": "a"}, {"_id": "60affb5c24a88c4e76aeb494c9f9e7d6", "standoff_subreadings": ["F"], "details": "lac", "text": [], "created": true, "suffixes": [""], "SR_text": {"F": {"details": "lac verse", "text": [], "type": "lac_verse"}}, "witnesses": ["F"], "type": "lac", "label": "zz"}], "start": 48, "_id": "343f503cbbc5d1972cfcc1767feed4d0"}, {"end": 54, "first_word_index": "54.1", "readings": [{"_id": "5d93246393e58468775fb70c34f6c77b", "witnesses": ["E2", "S", "Ss"], "text": [{"interface": "y", "E2": {"original": "y", "index": "54", "rule_match": ["y"], "t": "y"}, "Ss": {"original": "y", "index": "58", "rule_match": ["y"], "t": "y"}, "index": "54.1", "S": {"original": "y", "index": "54", "rule_match": ["y"], "t": "y"}, "reading": ["E2", "S", "Ss"]}], "suffixes": ["", "", ""], "label": "a"}, {"_id": "4abf17b49b7bb1f91c311f8cd6d4c7fb", "suffixes": [""], "text": [], "witnesses": ["D"], "type": "om", "label": "b"}, {"_id": "1a9f87f1c5d568f947e79f5f5f66ac83", "standoff_subreadings": ["F"], "details": "lac", "text": [], "created": true, "suffixes": [""], "SR_text": {"F": {"details": "lac verse", "text": [], "type": "lac_verse"}}, "witnesses": ["F"], "type": "lac", "label": "zz"}], "start": 54, "_id": "06c20dcb6c6149ab4cb8d8da845d393d"}, {"end": 66, "first_word_index": "56", "readings": [{"_id": "df15a489eba30278ff056b41c8033464", "witnesses": ["D", "E2", "S", "Ss"], "text": [{"interface": "dentro", "D": {"original": "dent\u00ba", "fullxml": "dent<am>\u00ba</am><ex>ro</ex>", "expanded": "dentro", "index": "60", "rule_match": ["dentro", "dent\u00ba", "dent<am>\u00ba</am><ex>ro</ex>"], "t": "dent\u00ba"}, "E2": {"original": "dentro", "index": "56", "rule_match": ["dentro"], "t": "dentro"}, "Ss": {"original": "dentro", "index": "60", "rule_match": ["dentro"], "t": "dentro"}, "index": "56", "S": {"original": "dentro", "index": "56", "rule_match": ["dentro"], "t": "dentro"}, "reading": ["D", "E2", "S", "Ss"]}, {"interface": "el", "D": {"original": "el", "index": "62", "rule_match": ["el"], "t": "el"}, "E2": {"original": "el", "index": "58", "rule_match": ["el"], "t": "el"}, "Ss": {"original": "el", "index": "62", "rule_match": ["el"], "t": "el"}, "index": "58", "S": {"original": "el", "index": "58", "rule_match": ["el"], "t": "el"}, "reading": ["D", "E2", "S", "Ss"]}, {"interface": "rey", "D": {"original": "rrey", "fullxml": "<choice><abbr><am><g>rr</g></am></abbr><expan><ex>R</ex></expan></choice>ey", "expanded": "Rey", "index": "64", "rule_match": ["Rey", "rrey", "<choice><abbr><am><g>rr</g></am></abbr><expan><ex>R</ex></expan></choice>ey", "rey", "<choice><abbr><am><g>rr</g></am></abbr><expan><ex>r</ex></expan></choice>ey"], "t": "rrey"}, "E2": {"original": "Rey", "index": "60", "rule_match": ["Rey", "rey"], "t": "Rey"}, "Ss": {"original": "Rey", "n": "rey", "fullxml": "<choice><abbr><am><g>R</g></am></abbr><expan><ex>rr</ex></expan></choice>ey", "decision_details": [{"scope": "once", "_id": "verse_CPSF:entity=1074:block=1900_6f04c5ff-9bfe-4aef-a9ef-8e2127230794", "n": "rey", "t": "rrey", "class": "none"}], "expanded": "rrey", "decision_class": ["none"], "index": "64", "rule_match": ["rrey", "Rey", "<choice><abbr><am><g>R</g></am></abbr><expan><ex>rr</ex></expan></choice>ey", "<choice><abbr><am><g>r</g></am></abbr><expan><ex>rr</ex></expan></choice>ey"], "t": "Rey"}, "index": "60", "S": {"original": "rrey", "fullxml": "<choice><abbr><am><g>rr</g></am></abbr><expan><ex>R</ex></expan></choice>ey", "expanded": "Rey", "index": "60", "rule_match": ["Rey", "rrey", "<choice><abbr><am><g>rr</g></am></abbr><expan><ex>R</ex></expan></choice>ey", "rey", "<choice><abbr><am><g>rr</g></am></abbr><expan><ex>r</ex></expan></choice>ey"], "t": "rrey"}, "reading": ["D", "E2", "S", "Ss"]}, {"interface": "de", "D": {"original": "de", "index": "66", "rule_match": ["de"], "t": "de"}, "E2": {"original": "de", "index": "62", "rule_match": ["de"], "t": "de"}, "Ss": {"original": "de", "index": "66", "rule_match": ["de"], "t": "de"}, "index": "62", "S": {"original": "de", "index": "62", "rule_match": ["de"], "t": "de"}, "reading": ["D", "E2", "S", "Ss"]}, {"interface": "granada", "D": {"original": "granada", "index": "68", "rule_match": ["granada"], "t": "granada"}, "E2": {"original": "granada", "index": "64", "rule_match": ["granada"], "t": "granada"}, "Ss": {"original": "granada", "index": "68", "rule_match": ["granada"], "t": "granada"}, "index": "64", "S": {"original": "granada", "index": "64", "rule_match": ["granada"], "t": "granada"}, "reading": ["D", "E2", "S", "Ss"]}, {"interface": "con", "D": {"original": "con", "index": "70", "rule_match": ["con"], "t": "con"}, "E2": {"original": "con", "index": "66", "rule_match": ["con"], "t": "con"}, "Ss": {"original": "con", "index": "70", "rule_match": ["con"], "t": "con"}, "index": "66", "S": {"original": "con", "index": "66", "rule_match": ["con"], "t": "con"}, "reading": ["D", "E2", "S", "Ss"]}], "suffixes": ["", "", "", ""], "label": "a"}, {"_id": "4f13ffc061fa25039cc0d8a0c9457ff0", "standoff_subreadings": ["F"], "details": "lac", "text": [], "created": true, "suffixes": [""], "SR_text": {"F": {"details": "lac verse", "text": [], "type": "lac_verse"}}, "witnesses": ["F"], "type": "lac", "label": "zz"}], "start": 56, "_id": "5e5a8db21553038b52958be710941f93"}, {"end": 68, "first_word_index": "68.1", "readings": [{"_id": "05088cd6ea2d9381c81e5bfd38816725", "witnesses": ["D", "E2", "S", "Ss"], "text": [{"interface": "ocho\u00e7ientos", "D": {"original": "ocho\u00e7ientos", "index": "72", "rule_match": ["ocho\u00e7ientos"], "t": "ocho\u00e7ientos"}, "E2": {"original": "ocho\u00e7ie\u0304tos", "fullxml": "ocho\u00e7ie<am>\u0304</am><ex>n</ex>tos", "expanded": "ocho\u00e7ientos", "index": "68", "rule_match": ["ocho\u00e7ientos", "ocho\u00e7ie\u0304tos", "ocho\u00e7ie<am>\u0304</am><ex>n</ex>tos"], "t": "ocho\u00e7ie\u0304tos"}, "Ss": {"original": "ocho\u00e7ientos", "index": "72", "rule_match": ["ocho\u00e7ientos"], "t": "ocho\u00e7ientos"}, "index": "68.1", "S": {"original": "ocho\u00e7ientos", "index": "68", "rule_match": ["ocho\u00e7ientos"], "t": "ocho\u00e7ientos"}, "reading": ["E2", "D", "S", "Ss"]}], "suffixes": ["", "", "", ""], "label": "a"}, {"_id": "e7b8da42cd69456ab87ab944eed66605", "standoff_subreadings": ["F"], "details": "lac", "text": [], "created": true, "suffixes": [""], "SR_text": {"F": {"details": "lac verse", "text": [], "type": "lac_verse"}}, "witnesses": ["F"], "type": "lac", "label": "zz"}], "start": 68, "_id": "1917718ca19f74baadae33446e1f7931"}, {"end": 70, "first_word_index": "70.1", "readings": [{"_id": "8112357949a02d6d032ad08f6d14c227", "standoff_subreadings": ["D", "Ss"], "text": [{"interface": "caua&lt;am&gt;\u0142\u0142&lt;/am&gt;&lt;ex&gt;ller&lt;/ex&gt;os", "index": "70.1", "E2": {"original": "ocho\u00e7ie\u0304tos", "fullxml": "caua<am>\u0142\u0142</am><ex>ller</ex>os", "expanded": "caua<am>\u0142\u0142</am><ex>ller</ex>os", "index": "70", "rule_match": ["caua<am>\u0142\u0142</am><ex>ller</ex>os", "ocho\u00e7ie\u0304tos", "caua<am>\u0142\u0142</am><ex>ller</ex>os"], "t": "ocho\u00e7ie\u0304tos"}, "S": {"original": "rrey", "fullxml": "caua<am>\u0142\u0142</am><ex>ller</ex>os", "expanded": "caua<am>\u0142\u0142</am><ex>ller</ex>os", "index": "70", "rule_match": ["caua<am>\u0142\u0142</am><ex>ller</ex>os", "rrey", "caua<am>\u0142\u0142</am><ex>ller</ex>os"], "t": "rrey"}, "reading": ["E2", "S"]}], "SR_text": {"Ss": {"text": [{"Ss": {"original": "caualleros", "index": "74", "rule_match": ["caualleros"], "interface": "caualleros", "t": "caualleros"}, "index": "70.1", "interface": "caualleros", "reading": ["Ss"]}]}, "D": {"text": [{"interface": "caua&lt;am&gt;\u0304&lt;/am&gt;lloscauall&lt;ex&gt;er&lt;/ex&gt;os", "index": "70.1", "reading": ["D"], "D": {"original": "rrey", "interface": "caua&lt;am&gt;\u0304&lt;/am&gt;lloscauall&lt;ex&gt;er&lt;/ex&gt;os", "fullxml": "<choice><abbr>caua<am>\u0304</am>llos</abbr><expan>cauall<ex>er</ex>os</expan></choice>", "expanded": "caua<am>\u0304</am>lloscauall<ex>er</ex>os", "index": "74", "rule_match": ["caua<am>\u0304</am>lloscauall<ex>er</ex>os", "rrey", "<choice><abbr>caua<am>\u0304</am>llos</abbr><expan>cauall<ex>er</ex>os</expan></choice>"], "t": "rrey"}}]}}, "witnesses": ["D", "E2", "S", "Ss"], "suffixes": ["r", "", "", "r"], "label": "a"}, {"_id": "d0382e1274aec182199546e79629184a", "standoff_subreadings": ["F"], "details": "lac", "text": [], "created": true, "suffixes": [""], "SR_text": {"F": {"details": "lac verse", "text": [], "type": "lac_verse"}}, "witnesses": ["F"], "type": "lac", "label": "zz"}], "start": 70, "_id": "9813f0fbb7e1fbc7be000d8c3efd6446"}], "lac_readings": ["F"], "om_readings": []}, "algorithm_settings": {"algorithm": "auto", "fuzzy_match": true, "distance": 2}, "TC_context": "CPSF:entity=1074:block=1900", "data_settings": {"base_text": "E2", "base_text_siglum": "E2", "witness_list": ["E2", "D", "F", "S", "Ss"], "language": "undefined"}, "user": "default", "status": "approved"}